{"v":"5.9.0","fr":24,"ip":0,"op":115,"w":450,"h":450,"nm":"loader","ddd":0,"assets":[{"id":"comp_0","nm":"fence","fr":24,"layers":[{"ddd":0,"ind":1,"ty":4,"nm":"Fence Outlines 2","sr":1,"ks":{"o":{"a":0,"k":100,"ix":11},"r":{"a":0,"k":0,"ix":10},"p":{"a":1,"k":[{"i":{"x":0.833,"y":0.833},"o":{"x":0.167,"y":0.167},"t":0,"s":[563,225,0],"to":[-58,0,0],"ti":[58,0,0]},{"t":118,"s":[215,225,0]}],"ix":2,"l":2},"a":{"a":0,"k":[225,225,0],"ix":1,"l":2},"s":{"a":0,"k":[100,100,100],"ix":6,"l":2}},"ao":0,"shapes":[{"ty":"gr","it":[{"ind":0,"ty":"sh","ix":1,"ks":{"a":0,"k":{"i":[[0,0],[0,0],[0,0],[0,0]],"o":[[0,0],[0,0],[0,0],[0,0]],"v":[[172.987,2.497],[-172.987,2.497],[-172.987,-2.497],[172.987,-2.497]],"c":true},"ix":2},"nm":"Path 1","mn":"ADBE Vector Shape - Group","hd":false},{"ty":"fl","c":{"a":0,"k":[0.949019667682,0.917647118662,0.854902020623,1],"ix":4},"o":{"a":0,"k":100,"ix":5},"r":1,"bm":0,"nm":"Fill 1","mn":"ADBE Vector Graphic - Fill","hd":false},{"ty":"tr","p":{"a":0,"k":[223.27,277.651],"ix":2},"a":{"a":0,"k":[0,0],"ix":1},"s":{"a":0,"k":[100,100],"ix":3},"r":{"a":0,"k":0,"ix":6},"o":{"a":0,"k":100,"ix":7},"sk":{"a":0,"k":0,"ix":4},"sa":{"a":0,"k":0,"ix":5},"nm":"Transform"}],"nm":"Group 1","np":2,"cix":2,"bm":0,"ix":1,"mn":"ADBE Vector Group","hd":false},{"ty":"gr","it":[{"ind":0,"ty":"sh","ix":1,"ks":{"a":0,"k":{"i":[[0,0],[0,0],[0,0],[0,0]],"o":[[0,0],[0,0],[0,0],[0,0]],"v":[[172.987,2.497],[-172.987,2.497],[-172.987,-2.497],[172.987,-2.497]],"c":true},"ix":2},"nm":"Path 1","mn":"ADBE Vector Shape - Group","hd":false},{"ty":"fl","c":{"a":0,"k":[0.949019667682,0.917647118662,0.854902020623,1],"ix":4},"o":{"a":0,"k":100,"ix":5},"r":1,"bm":0,"nm":"Fill 1","mn":"ADBE Vector Graphic - Fill","hd":false},{"ty":"tr","p":{"a":0,"k":[223.27,233.809],"ix":2},"a":{"a":0,"k":[0,0],"ix":1},"s":{"a":0,"k":[100,100],"ix":3},"r":{"a":0,"k":0,"ix":6},"o":{"a":0,"k":100,"ix":7},"sk":{"a":0,"k":0,"ix":4},"sa":{"a":0,"k":0,"ix":5},"nm":"Transform"}],"nm":"Group 2","np":2,"cix":2,"bm":0,"ix":2,"mn":"ADBE Vector Group","hd":false},{"ty":"gr","it":[{"ind":0,"ty":"sh","ix":1,"ks":{"a":0,"k":{"i":[[0,0],[0,0],[0,0],[0,0],[-0.352,-0.427],[0,0]],"o":[[0,0],[0,0],[0,0],[0.352,-0.427],[0,0],[0,0]],"v":[[6.242,41.042],[-6.242,41.042],[-6.242,-33.861],[-0.68,-40.615],[0.68,-40.615],[6.242,-33.861]],"c":true},"ix":2},"nm":"Path 1","mn":"ADBE Vector Shape - Group","hd":false},{"ty":"fl","c":{"a":0,"k":[0.949019667682,0.917647118662,0.854902020623,1],"ix":4},"o":{"a":0,"k":100,"ix":5},"r":1,"bm":0,"nm":"Fill 1","mn":"ADBE Vector Graphic - Fill","hd":false},{"ty":"tr","p":{"a":0,"k":[65.974,250.803],"ix":2},"a":{"a":0,"k":[0,0],"ix":1},"s":{"a":0,"k":[100,100],"ix":3},"r":{"a":0,"k":0,"ix":6},"o":{"a":0,"k":100,"ix":7},"sk":{"a":0,"k":0,"ix":4},"sa":{"a":0,"k":0,"ix":5},"nm":"Transform"}],"nm":"Group 3","np":2,"cix":2,"bm":0,"ix":3,"mn":"ADBE Vector Group","hd":false},{"ty":"gr","it":[{"ind":0,"ty":"sh","ix":1,"ks":{"a":0,"k":{"i":[[0,0],[0,0],[0,0],[0,0],[-0.352,-0.427],[0,0]],"o":[[0,0],[0,0],[0,0],[0.352,-0.427],[0,0],[0,0]],"v":[[6.242,41.042],[-6.242,41.042],[-6.242,-33.861],[-0.68,-40.615],[0.68,-40.615],[6.242,-33.861]],"c":true},"ix":2},"nm":"Path 1","mn":"ADBE Vector Shape - Group","hd":false},{"ty":"fl","c":{"a":0,"k":[0.949019667682,0.917647118662,0.854902020623,1],"ix":4},"o":{"a":0,"k":100,"ix":5},"r":1,"bm":0,"nm":"Fill 1","mn":"ADBE Vector Graphic - Fill","hd":false},{"ty":"tr","p":{"a":0,"k":[92.19,250.803],"ix":2},"a":{"a":0,"k":[0,0],"ix":1},"s":{"a":0,"k":[100,100],"ix":3},"r":{"a":0,"k":0,"ix":6},"o":{"a":0,"k":100,"ix":7},"sk":{"a":0,"k":0,"ix":4},"sa":{"a":0,"k":0,"ix":5},"nm":"Transform"}],"nm":"Group 4","np":2,"cix":2,"bm":0,"ix":4,"mn":"ADBE Vector Group","hd":false},{"ty":"gr","it":[{"ind":0,"ty":"sh","ix":1,"ks":{"a":0,"k":{"i":[[0,0],[0,0],[0,0],[0,0],[-0.352,-0.427],[0,0]],"o":[[0,0],[0,0],[0,0],[0.352,-0.427],[0,0],[0,0]],"v":[[6.242,41.042],[-6.242,41.042],[-6.242,-33.861],[-0.68,-40.615],[0.68,-40.615],[6.242,-33.861]],"c":true},"ix":2},"nm":"Path 1","mn":"ADBE Vector Shape - Group","hd":false},{"ty":"fl","c":{"a":0,"k":[0.949019667682,0.917647118662,0.854902020623,1],"ix":4},"o":{"a":0,"k":100,"ix":5},"r":1,"bm":0,"nm":"Fill 1","mn":"ADBE Vector Graphic - Fill","hd":false},{"ty":"tr","p":{"a":0,"k":[118.406,250.803],"ix":2},"a":{"a":0,"k":[0,0],"ix":1},"s":{"a":0,"k":[100,100],"ix":3},"r":{"a":0,"k":0,"ix":6},"o":{"a":0,"k":100,"ix":7},"sk":{"a":0,"k":0,"ix":4},"sa":{"a":0,"k":0,"ix":5},"nm":"Transform"}],"nm":"Group 5","np":2,"cix":2,"bm":0,"ix":5,"mn":"ADBE Vector Group","hd":false},{"ty":"gr","it":[{"ind":0,"ty":"sh","ix":1,"ks":{"a":0,"k":{"i":[[0,0],[0,0],[0,0],[0,0],[-0.352,-0.427],[0,0]],"o":[[0,0],[0,0],[0,0],[0.352,-0.427],[0,0],[0,0]],"v":[[6.242,41.042],[-6.242,41.042],[-6.242,-33.861],[-0.68,-40.615],[0.68,-40.615],[6.242,-33.861]],"c":true},"ix":2},"nm":"Path 1","mn":"ADBE Vector Shape - Group","hd":false},{"ty":"fl","c":{"a":0,"k":[0.949019667682,0.917647118662,0.854902020623,1],"ix":4},"o":{"a":0,"k":100,"ix":5},"r":1,"bm":0,"nm":"Fill 1","mn":"ADBE Vector Graphic - Fill","hd":false},{"ty":"tr","p":{"a":0,"k":[144.622,250.803],"ix":2},"a":{"a":0,"k":[0,0],"ix":1},"s":{"a":0,"k":[100,100],"ix":3},"r":{"a":0,"k":0,"ix":6},"o":{"a":0,"k":100,"ix":7},"sk":{"a":0,"k":0,"ix":4},"sa":{"a":0,"k":0,"ix":5},"nm":"Transform"}],"nm":"Group 6","np":2,"cix":2,"bm":0,"ix":6,"mn":"ADBE Vector Group","hd":false},{"ty":"gr","it":[{"ind":0,"ty":"sh","ix":1,"ks":{"a":0,"k":{"i":[[0,0],[0,0],[0,0],[0,0],[-0.352,-0.427],[0,0]],"o":[[0,0],[0,0],[0,0],[0.352,-0.427],[0,0],[0,0]],"v":[[6.242,41.042],[-6.242,41.042],[-6.242,-33.861],[-0.68,-40.615],[0.68,-40.615],[6.242,-33.861]],"c":true},"ix":2},"nm":"Path 1","mn":"ADBE Vector Shape - Group","hd":false},{"ty":"fl","c":{"a":0,"k":[0.949019667682,0.917647118662,0.854902020623,1],"ix":4},"o":{"a":0,"k":100,"ix":5},"r":1,"bm":0,"nm":"Fill 1","mn":"ADBE Vector Graphic - Fill","hd":false},{"ty":"tr","p":{"a":0,"k":[170.838,250.803],"ix":2},"a":{"a":0,"k":[0,0],"ix":1},"s":{"a":0,"k":[100,100],"ix":3},"r":{"a":0,"k":0,"ix":6},"o":{"a":0,"k":100,"ix":7},"sk":{"a":0,"k":0,"ix":4},"sa":{"a":0,"k":0,"ix":5},"nm":"Transform"}],"nm":"Group 7","np":2,"cix":2,"bm":0,"ix":7,"mn":"ADBE Vector Group","hd":false},{"ty":"gr","it":[{"ind":0,"ty":"sh","ix":1,"ks":{"a":0,"k":{"i":[[0,0],[0,0],[0,0],[0,0],[-0.352,-0.427],[0,0]],"o":[[0,0],[0,0],[0,0],[0.352,-0.427],[0,0],[0,0]],"v":[[6.242,41.042],[-6.242,41.042],[-6.242,-33.861],[-0.68,-40.615],[0.68,-40.615],[6.242,-33.861]],"c":true},"ix":2},"nm":"Path 1","mn":"ADBE Vector Shape - Group","hd":false},{"ty":"fl","c":{"a":0,"k":[0.949019667682,0.917647118662,0.854902020623,1],"ix":4},"o":{"a":0,"k":100,"ix":5},"r":1,"bm":0,"nm":"Fill 1","mn":"ADBE Vector Graphic - Fill","hd":false},{"ty":"tr","p":{"a":0,"k":[197.054,250.803],"ix":2},"a":{"a":0,"k":[0,0],"ix":1},"s":{"a":0,"k":[100,100],"ix":3},"r":{"a":0,"k":0,"ix":6},"o":{"a":0,"k":100,"ix":7},"sk":{"a":0,"k":0,"ix":4},"sa":{"a":0,"k":0,"ix":5},"nm":"Transform"}],"nm":"Group 8","np":2,"cix":2,"bm":0,"ix":8,"mn":"ADBE Vector Group","hd":false},{"ty":"gr","it":[{"ind":0,"ty":"sh","ix":1,"ks":{"a":0,"k":{"i":[[0,0],[0,0],[0,0],[0,0],[-0.352,-0.427],[0,0]],"o":[[0,0],[0,0],[0,0],[0.352,-0.427],[0,0],[0,0]],"v":[[6.242,41.042],[-6.242,41.042],[-6.242,-33.861],[-0.68,-40.615],[0.68,-40.615],[6.242,-33.861]],"c":true},"ix":2},"nm":"Path 1","mn":"ADBE Vector Shape - Group","hd":false},{"ty":"fl","c":{"a":0,"k":[0.949019667682,0.917647118662,0.854902020623,1],"ix":4},"o":{"a":0,"k":100,"ix":5},"r":1,"bm":0,"nm":"Fill 1","mn":"ADBE Vector Graphic - Fill","hd":false},{"ty":"tr","p":{"a":0,"k":[223.27,250.803],"ix":2},"a":{"a":0,"k":[0,0],"ix":1},"s":{"a":0,"k":[100,100],"ix":3},"r":{"a":0,"k":0,"ix":6},"o":{"a":0,"k":100,"ix":7},"sk":{"a":0,"k":0,"ix":4},"sa":{"a":0,"k":0,"ix":5},"nm":"Transform"}],"nm":"Group 9","np":2,"cix":2,"bm":0,"ix":9,"mn":"ADBE Vector Group","hd":false},{"ty":"gr","it":[{"ind":0,"ty":"sh","ix":1,"ks":{"a":0,"k":{"i":[[0,0],[0,0],[0,0],[0,0],[-0.352,-0.427],[0,0]],"o":[[0,0],[0,0],[0,0],[0.352,-0.427],[0,0],[0,0]],"v":[[6.242,41.042],[-6.242,41.042],[-6.242,-33.861],[-0.68,-40.615],[0.68,-40.615],[6.242,-33.861]],"c":true},"ix":2},"nm":"Path 1","mn":"ADBE Vector Shape - Group","hd":false},{"ty":"fl","c":{"a":0,"k":[0.949019667682,0.917647118662,0.854902020623,1],"ix":4},"o":{"a":0,"k":100,"ix":5},"r":1,"bm":0,"nm":"Fill 1","mn":"ADBE Vector Graphic - Fill","hd":false},{"ty":"tr","p":{"a":0,"k":[249.486,250.803],"ix":2},"a":{"a":0,"k":[0,0],"ix":1},"s":{"a":0,"k":[100,100],"ix":3},"r":{"a":0,"k":0,"ix":6},"o":{"a":0,"k":100,"ix":7},"sk":{"a":0,"k":0,"ix":4},"sa":{"a":0,"k":0,"ix":5},"nm":"Transform"}],"nm":"Group 10","np":2,"cix":2,"bm":0,"ix":10,"mn":"ADBE Vector Group","hd":false},{"ty":"gr","it":[{"ind":0,"ty":"sh","ix":1,"ks":{"a":0,"k":{"i":[[0,0],[0,0],[0,0],[0,0],[-0.352,-0.427],[0,0]],"o":[[0,0],[0,0],[0,0],[0.352,-0.427],[0,0],[0,0]],"v":[[6.242,41.042],[-6.242,41.042],[-6.242,-33.861],[-0.68,-40.615],[0.68,-40.615],[6.242,-33.861]],"c":true},"ix":2},"nm":"Path 1","mn":"ADBE Vector Shape - Group","hd":false},{"ty":"fl","c":{"a":0,"k":[0.949019667682,0.917647118662,0.854902020623,1],"ix":4},"o":{"a":0,"k":100,"ix":5},"r":1,"bm":0,"nm":"Fill 1","mn":"ADBE Vector Graphic - Fill","hd":false},{"ty":"tr","p":{"a":0,"k":[275.702,250.803],"ix":2},"a":{"a":0,"k":[0,0],"ix":1},"s":{"a":0,"k":[100,100],"ix":3},"r":{"a":0,"k":0,"ix":6},"o":{"a":0,"k":100,"ix":7},"sk":{"a":0,"k":0,"ix":4},"sa":{"a":0,"k":0,"ix":5},"nm":"Transform"}],"nm":"Group 11","np":2,"cix":2,"bm":0,"ix":11,"mn":"ADBE Vector Group","hd":false},{"ty":"gr","it":[{"ind":0,"ty":"sh","ix":1,"ks":{"a":0,"k":{"i":[[0,0],[0,0],[0,0],[0,0],[-0.352,-0.427],[0,0]],"o":[[0,0],[0,0],[0,0],[0.352,-0.427],[0,0],[0,0]],"v":[[6.242,41.042],[-6.242,41.042],[-6.242,-33.861],[-0.68,-40.615],[0.68,-40.615],[6.242,-33.861]],"c":true},"ix":2},"nm":"Path 1","mn":"ADBE Vector Shape - Group","hd":false},{"ty":"fl","c":{"a":0,"k":[0.949019667682,0.917647118662,0.854902020623,1],"ix":4},"o":{"a":0,"k":100,"ix":5},"r":1,"bm":0,"nm":"Fill 1","mn":"ADBE Vector Graphic - Fill","hd":false},{"ty":"tr","p":{"a":0,"k":[354.35,250.803],"ix":2},"a":{"a":0,"k":[0,0],"ix":1},"s":{"a":0,"k":[100,100],"ix":3},"r":{"a":0,"k":0,"ix":6},"o":{"a":0,"k":100,"ix":7},"sk":{"a":0,"k":0,"ix":4},"sa":{"a":0,"k":0,"ix":5},"nm":"Transform"}],"nm":"Group 12","np":2,"cix":2,"bm":0,"ix":12,"mn":"ADBE Vector Group","hd":false},{"ty":"gr","it":[{"ind":0,"ty":"sh","ix":1,"ks":{"a":0,"k":{"i":[[0,0],[0,0],[0,0],[0,0],[-0.352,-0.427],[0,0]],"o":[[0,0],[0,0],[0,0],[0.352,-0.427],[0,0],[0,0]],"v":[[6.242,41.042],[-6.242,41.042],[-6.242,-33.861],[-0.68,-40.615],[0.68,-40.615],[6.242,-33.861]],"c":true},"ix":2},"nm":"Path 1","mn":"ADBE Vector Shape - Group","hd":false},{"ty":"fl","c":{"a":0,"k":[0.949019667682,0.917647118662,0.854902020623,1],"ix":4},"o":{"a":0,"k":100,"ix":5},"r":1,"bm":0,"nm":"Fill 1","mn":"ADBE Vector Graphic - Fill","hd":false},{"ty":"tr","p":{"a":0,"k":[380.566,250.803],"ix":2},"a":{"a":0,"k":[0,0],"ix":1},"s":{"a":0,"k":[100,100],"ix":3},"r":{"a":0,"k":0,"ix":6},"o":{"a":0,"k":100,"ix":7},"sk":{"a":0,"k":0,"ix":4},"sa":{"a":0,"k":0,"ix":5},"nm":"Transform"}],"nm":"Group 13","np":2,"cix":2,"bm":0,"ix":13,"mn":"ADBE Vector Group","hd":false},{"ty":"gr","it":[{"ind":0,"ty":"sh","ix":1,"ks":{"a":0,"k":{"i":[[0,0],[0,0],[0,0],[0,0],[-0.352,-0.427],[0,0]],"o":[[0,0],[0,0],[0,0],[0.352,-0.427],[0,0],[0,0]],"v":[[6.242,41.042],[-6.242,41.042],[-6.242,-33.861],[-0.68,-40.615],[0.68,-40.615],[6.242,-33.861]],"c":true},"ix":2},"nm":"Path 1","mn":"ADBE Vector Shape - Group","hd":false},{"ty":"fl","c":{"a":0,"k":[0.949019667682,0.917647118662,0.854902020623,1],"ix":4},"o":{"a":0,"k":100,"ix":5},"r":1,"bm":0,"nm":"Fill 1","mn":"ADBE Vector Graphic - Fill","hd":false},{"ty":"tr","p":{"a":0,"k":[301.918,250.803],"ix":2},"a":{"a":0,"k":[0,0],"ix":1},"s":{"a":0,"k":[100,100],"ix":3},"r":{"a":0,"k":0,"ix":6},"o":{"a":0,"k":100,"ix":7},"sk":{"a":0,"k":0,"ix":4},"sa":{"a":0,"k":0,"ix":5},"nm":"Transform"}],"nm":"Group 14","np":2,"cix":2,"bm":0,"ix":14,"mn":"ADBE Vector Group","hd":false},{"ty":"gr","it":[{"ind":0,"ty":"sh","ix":1,"ks":{"a":0,"k":{"i":[[0,0],[0,0],[0,0],[0,0],[-0.352,-0.427],[0,0]],"o":[[0,0],[0,0],[0,0],[0.352,-0.427],[0,0],[0,0]],"v":[[6.242,41.042],[-6.242,41.042],[-6.242,-33.861],[-0.68,-40.615],[0.68,-40.615],[6.242,-33.861]],"c":true},"ix":2},"nm":"Path 1","mn":"ADBE Vector Shape - Group","hd":false},{"ty":"fl","c":{"a":0,"k":[0.949019667682,0.917647118662,0.854902020623,1],"ix":4},"o":{"a":0,"k":100,"ix":5},"r":1,"bm":0,"nm":"Fill 1","mn":"ADBE Vector Graphic - Fill","hd":false},{"ty":"tr","p":{"a":0,"k":[328.134,250.803],"ix":2},"a":{"a":0,"k":[0,0],"ix":1},"s":{"a":0,"k":[100,100],"ix":3},"r":{"a":0,"k":0,"ix":6},"o":{"a":0,"k":100,"ix":7},"sk":{"a":0,"k":0,"ix":4},"sa":{"a":0,"k":0,"ix":5},"nm":"Transform"}],"nm":"Group 15","np":2,"cix":2,"bm":0,"ix":15,"mn":"ADBE Vector Group","hd":false}],"ip":0,"op":118,"st":0,"bm":0},{"ddd":0,"ind":2,"ty":4,"nm":"Fence Outlines","sr":1,"ks":{"o":{"a":0,"k":100,"ix":11},"r":{"a":0,"k":0,"ix":10},"p":{"a":1,"k":[{"i":{"x":0.833,"y":0.833},"o":{"x":0.167,"y":0.167},"t":0,"s":[225,225,0],"to":[-58,0,0],"ti":[58,0,0]},{"t":118,"s":[-123,225,0]}],"ix":2,"l":2},"a":{"a":0,"k":[225,225,0],"ix":1,"l":2},"s":{"a":0,"k":[100,100,100],"ix":6,"l":2}},"ao":0,"shapes":[{"ty":"gr","it":[{"ind":0,"ty":"sh","ix":1,"ks":{"a":0,"k":{"i":[[0,0],[0,0],[0,0],[0,0]],"o":[[0,0],[0,0],[0,0],[0,0]],"v":[[172.987,2.497],[-172.987,2.497],[-172.987,-2.497],[172.987,-2.497]],"c":true},"ix":2},"nm":"Path 1","mn":"ADBE Vector Shape - Group","hd":false},{"ty":"fl","c":{"a":0,"k":[0.949019667682,0.917647118662,0.854902020623,1],"ix":4},"o":{"a":0,"k":100,"ix":5},"r":1,"bm":0,"nm":"Fill 1","mn":"ADBE Vector Graphic - Fill","hd":false},{"ty":"tr","p":{"a":0,"k":[223.27,277.651],"ix":2},"a":{"a":0,"k":[0,0],"ix":1},"s":{"a":0,"k":[100,100],"ix":3},"r":{"a":0,"k":0,"ix":6},"o":{"a":0,"k":100,"ix":7},"sk":{"a":0,"k":0,"ix":4},"sa":{"a":0,"k":0,"ix":5},"nm":"Transform"}],"nm":"Group 1","np":2,"cix":2,"bm":0,"ix":1,"mn":"ADBE Vector Group","hd":false},{"ty":"gr","it":[{"ind":0,"ty":"sh","ix":1,"ks":{"a":0,"k":{"i":[[0,0],[0,0],[0,0],[0,0]],"o":[[0,0],[0,0],[0,0],[0,0]],"v":[[172.987,2.497],[-172.987,2.497],[-172.987,-2.497],[172.987,-2.497]],"c":true},"ix":2},"nm":"Path 1","mn":"ADBE Vector Shape - Group","hd":false},{"ty":"fl","c":{"a":0,"k":[0.949019667682,0.917647118662,0.854902020623,1],"ix":4},"o":{"a":0,"k":100,"ix":5},"r":1,"bm":0,"nm":"Fill 1","mn":"ADBE Vector Graphic - Fill","hd":false},{"ty":"tr","p":{"a":0,"k":[223.27,233.809],"ix":2},"a":{"a":0,"k":[0,0],"ix":1},"s":{"a":0,"k":[100,100],"ix":3},"r":{"a":0,"k":0,"ix":6},"o":{"a":0,"k":100,"ix":7},"sk":{"a":0,"k":0,"ix":4},"sa":{"a":0,"k":0,"ix":5},"nm":"Transform"}],"nm":"Group 2","np":2,"cix":2,"bm":0,"ix":2,"mn":"ADBE Vector Group","hd":false},{"ty":"gr","it":[{"ind":0,"ty":"sh","ix":1,"ks":{"a":0,"k":{"i":[[0,0],[0,0],[0,0],[0,0],[-0.352,-0.427],[0,0]],"o":[[0,0],[0,0],[0,0],[0.352,-0.427],[0,0],[0,0]],"v":[[6.242,41.042],[-6.242,41.042],[-6.242,-33.861],[-0.68,-40.615],[0.68,-40.615],[6.242,-33.861]],"c":true},"ix":2},"nm":"Path 1","mn":"ADBE Vector Shape - Group","hd":false},{"ty":"fl","c":{"a":0,"k":[0.949019667682,0.917647118662,0.854902020623,1],"ix":4},"o":{"a":0,"k":100,"ix":5},"r":1,"bm":0,"nm":"Fill 1","mn":"ADBE Vector Graphic - Fill","hd":false},{"ty":"tr","p":{"a":0,"k":[65.974,250.803],"ix":2},"a":{"a":0,"k":[0,0],"ix":1},"s":{"a":0,"k":[100,100],"ix":3},"r":{"a":0,"k":0,"ix":6},"o":{"a":0,"k":100,"ix":7},"sk":{"a":0,"k":0,"ix":4},"sa":{"a":0,"k":0,"ix":5},"nm":"Transform"}],"nm":"Group 3","np":2,"cix":2,"bm":0,"ix":3,"mn":"ADBE Vector Group","hd":false},{"ty":"gr","it":[{"ind":0,"ty":"sh","ix":1,"ks":{"a":0,"k":{"i":[[0,0],[0,0],[0,0],[0,0],[-0.352,-0.427],[0,0]],"o":[[0,0],[0,0],[0,0],[0.352,-0.427],[0,0],[0,0]],"v":[[6.242,41.042],[-6.242,41.042],[-6.242,-33.861],[-0.68,-40.615],[0.68,-40.615],[6.242,-33.861]],"c":true},"ix":2},"nm":"Path 1","mn":"ADBE Vector Shape - Group","hd":false},{"ty":"fl","c":{"a":0,"k":[0.949019667682,0.917647118662,0.854902020623,1],"ix":4},"o":{"a":0,"k":100,"ix":5},"r":1,"bm":0,"nm":"Fill 1","mn":"ADBE Vector Graphic - Fill","hd":false},{"ty":"tr","p":{"a":0,"k":[92.19,250.803],"ix":2},"a":{"a":0,"k":[0,0],"ix":1},"s":{"a":0,"k":[100,100],"ix":3},"r":{"a":0,"k":0,"ix":6},"o":{"a":0,"k":100,"ix":7},"sk":{"a":0,"k":0,"ix":4},"sa":{"a":0,"k":0,"ix":5},"nm":"Transform"}],"nm":"Group 4","np":2,"cix":2,"bm":0,"ix":4,"mn":"ADBE Vector Group","hd":false},{"ty":"gr","it":[{"ind":0,"ty":"sh","ix":1,"ks":{"a":0,"k":{"i":[[0,0],[0,0],[0,0],[0,0],[-0.352,-0.427],[0,0]],"o":[[0,0],[0,0],[0,0],[0.352,-0.427],[0,0],[0,0]],"v":[[6.242,41.042],[-6.242,41.042],[-6.242,-33.861],[-0.68,-40.615],[0.68,-40.615],[6.242,-33.861]],"c":true},"ix":2},"nm":"Path 1","mn":"ADBE Vector Shape - Group","hd":false},{"ty":"fl","c":{"a":0,"k":[0.949019667682,0.917647118662,0.854902020623,1],"ix":4},"o":{"a":0,"k":100,"ix":5},"r":1,"bm":0,"nm":"Fill 1","mn":"ADBE Vector Graphic - Fill","hd":false},{"ty":"tr","p":{"a":0,"k":[118.406,250.803],"ix":2},"a":{"a":0,"k":[0,0],"ix":1},"s":{"a":0,"k":[100,100],"ix":3},"r":{"a":0,"k":0,"ix":6},"o":{"a":0,"k":100,"ix":7},"sk":{"a":0,"k":0,"ix":4},"sa":{"a":0,"k":0,"ix":5},"nm":"Transform"}],"nm":"Group 5","np":2,"cix":2,"bm":0,"ix":5,"mn":"ADBE Vector Group","hd":false},{"ty":"gr","it":[{"ind":0,"ty":"sh","ix":1,"ks":{"a":0,"k":{"i":[[0,0],[0,0],[0,0],[0,0],[-0.352,-0.427],[0,0]],"o":[[0,0],[0,0],[0,0],[0.352,-0.427],[0,0],[0,0]],"v":[[6.242,41.042],[-6.242,41.042],[-6.242,-33.861],[-0.68,-40.615],[0.68,-40.615],[6.242,-33.861]],"c":true},"ix":2},"nm":"Path 1","mn":"ADBE Vector Shape - Group","hd":false},{"ty":"fl","c":{"a":0,"k":[0.949019667682,0.917647118662,0.854902020623,1],"ix":4},"o":{"a":0,"k":100,"ix":5},"r":1,"bm":0,"nm":"Fill 1","mn":"ADBE Vector Graphic - Fill","hd":false},{"ty":"tr","p":{"a":0,"k":[144.622,250.803],"ix":2},"a":{"a":0,"k":[0,0],"ix":1},"s":{"a":0,"k":[100,100],"ix":3},"r":{"a":0,"k":0,"ix":6},"o":{"a":0,"k":100,"ix":7},"sk":{"a":0,"k":0,"ix":4},"sa":{"a":0,"k":0,"ix":5},"nm":"Transform"}],"nm":"Group 6","np":2,"cix":2,"bm":0,"ix":6,"mn":"ADBE Vector Group","hd":false},{"ty":"gr","it":[{"ind":0,"ty":"sh","ix":1,"ks":{"a":0,"k":{"i":[[0,0],[0,0],[0,0],[0,0],[-0.352,-0.427],[0,0]],"o":[[0,0],[0,0],[0,0],[0.352,-0.427],[0,0],[0,0]],"v":[[6.242,41.042],[-6.242,41.042],[-6.242,-33.861],[-0.68,-40.615],[0.68,-40.615],[6.242,-33.861]],"c":true},"ix":2},"nm":"Path 1","mn":"ADBE Vector Shape - Group","hd":false},{"ty":"fl","c":{"a":0,"k":[0.949019667682,0.917647118662,0.854902020623,1],"ix":4},"o":{"a":0,"k":100,"ix":5},"r":1,"bm":0,"nm":"Fill 1","mn":"ADBE Vector Graphic - Fill","hd":false},{"ty":"tr","p":{"a":0,"k":[170.838,250.803],"ix":2},"a":{"a":0,"k":[0,0],"ix":1},"s":{"a":0,"k":[100,100],"ix":3},"r":{"a":0,"k":0,"ix":6},"o":{"a":0,"k":100,"ix":7},"sk":{"a":0,"k":0,"ix":4},"sa":{"a":0,"k":0,"ix":5},"nm":"Transform"}],"nm":"Group 7","np":2,"cix":2,"bm":0,"ix":7,"mn":"ADBE Vector Group","hd":false},{"ty":"gr","it":[{"ind":0,"ty":"sh","ix":1,"ks":{"a":0,"k":{"i":[[0,0],[0,0],[0,0],[0,0],[-0.352,-0.427],[0,0]],"o":[[0,0],[0,0],[0,0],[0.352,-0.427],[0,0],[0,0]],"v":[[6.242,41.042],[-6.242,41.042],[-6.242,-33.861],[-0.68,-40.615],[0.68,-40.615],[6.242,-33.861]],"c":true},"ix":2},"nm":"Path 1","mn":"ADBE Vector Shape - Group","hd":false},{"ty":"fl","c":{"a":0,"k":[0.949019667682,0.917647118662,0.854902020623,1],"ix":4},"o":{"a":0,"k":100,"ix":5},"r":1,"bm":0,"nm":"Fill 1","mn":"ADBE Vector Graphic - Fill","hd":false},{"ty":"tr","p":{"a":0,"k":[197.054,250.803],"ix":2},"a":{"a":0,"k":[0,0],"ix":1},"s":{"a":0,"k":[100,100],"ix":3},"r":{"a":0,"k":0,"ix":6},"o":{"a":0,"k":100,"ix":7},"sk":{"a":0,"k":0,"ix":4},"sa":{"a":0,"k":0,"ix":5},"nm":"Transform"}],"nm":"Group 8","np":2,"cix":2,"bm":0,"ix":8,"mn":"ADBE Vector Group","hd":false},{"ty":"gr","it":[{"ind":0,"ty":"sh","ix":1,"ks":{"a":0,"k":{"i":[[0,0],[0,0],[0,0],[0,0],[-0.352,-0.427],[0,0]],"o":[[0,0],[0,0],[0,0],[0.352,-0.427],[0,0],[0,0]],"v":[[6.242,41.042],[-6.242,41.042],[-6.242,-33.861],[-0.68,-40.615],[0.68,-40.615],[6.242,-33.861]],"c":true},"ix":2},"nm":"Path 1","mn":"ADBE Vector Shape - Group","hd":false},{"ty":"fl","c":{"a":0,"k":[0.949019667682,0.917647118662,0.854902020623,1],"ix":4},"o":{"a":0,"k":100,"ix":5},"r":1,"bm":0,"nm":"Fill 1","mn":"ADBE Vector Graphic - Fill","hd":false},{"ty":"tr","p":{"a":0,"k":[223.27,250.803],"ix":2},"a":{"a":0,"k":[0,0],"ix":1},"s":{"a":0,"k":[100,100],"ix":3},"r":{"a":0,"k":0,"ix":6},"o":{"a":0,"k":100,"ix":7},"sk":{"a":0,"k":0,"ix":4},"sa":{"a":0,"k":0,"ix":5},"nm":"Transform"}],"nm":"Group 9","np":2,"cix":2,"bm":0,"ix":9,"mn":"ADBE Vector Group","hd":false},{"ty":"gr","it":[{"ind":0,"ty":"sh","ix":1,"ks":{"a":0,"k":{"i":[[0,0],[0,0],[0,0],[0,0],[-0.352,-0.427],[0,0]],"o":[[0,0],[0,0],[0,0],[0.352,-0.427],[0,0],[0,0]],"v":[[6.242,41.042],[-6.242,41.042],[-6.242,-33.861],[-0.68,-40.615],[0.68,-40.615],[6.242,-33.861]],"c":true},"ix":2},"nm":"Path 1","mn":"ADBE Vector Shape - Group","hd":false},{"ty":"fl","c":{"a":0,"k":[0.949019667682,0.917647118662,0.854902020623,1],"ix":4},"o":{"a":0,"k":100,"ix":5},"r":1,"bm":0,"nm":"Fill 1","mn":"ADBE Vector Graphic - Fill","hd":false},{"ty":"tr","p":{"a":0,"k":[249.486,250.803],"ix":2},"a":{"a":0,"k":[0,0],"ix":1},"s":{"a":0,"k":[100,100],"ix":3},"r":{"a":0,"k":0,"ix":6},"o":{"a":0,"k":100,"ix":7},"sk":{"a":0,"k":0,"ix":4},"sa":{"a":0,"k":0,"ix":5},"nm":"Transform"}],"nm":"Group 10","np":2,"cix":2,"bm":0,"ix":10,"mn":"ADBE Vector Group","hd":false},{"ty":"gr","it":[{"ind":0,"ty":"sh","ix":1,"ks":{"a":0,"k":{"i":[[0,0],[0,0],[0,0],[0,0],[-0.352,-0.427],[0,0]],"o":[[0,0],[0,0],[0,0],[0.352,-0.427],[0,0],[0,0]],"v":[[6.242,41.042],[-6.242,41.042],[-6.242,-33.861],[-0.68,-40.615],[0.68,-40.615],[6.242,-33.861]],"c":true},"ix":2},"nm":"Path 1","mn":"ADBE Vector Shape - Group","hd":false},{"ty":"fl","c":{"a":0,"k":[0.949019667682,0.917647118662,0.854902020623,1],"ix":4},"o":{"a":0,"k":100,"ix":5},"r":1,"bm":0,"nm":"Fill 1","mn":"ADBE Vector Graphic - Fill","hd":false},{"ty":"tr","p":{"a":0,"k":[275.702,250.803],"ix":2},"a":{"a":0,"k":[0,0],"ix":1},"s":{"a":0,"k":[100,100],"ix":3},"r":{"a":0,"k":0,"ix":6},"o":{"a":0,"k":100,"ix":7},"sk":{"a":0,"k":0,"ix":4},"sa":{"a":0,"k":0,"ix":5},"nm":"Transform"}],"nm":"Group 11","np":2,"cix":2,"bm":0,"ix":11,"mn":"ADBE Vector Group","hd":false},{"ty":"gr","it":[{"ind":0,"ty":"sh","ix":1,"ks":{"a":0,"k":{"i":[[0,0],[0,0],[0,0],[0,0],[-0.352,-0.427],[0,0]],"o":[[0,0],[0,0],[0,0],[0.352,-0.427],[0,0],[0,0]],"v":[[6.242,41.042],[-6.242,41.042],[-6.242,-33.861],[-0.68,-40.615],[0.68,-40.615],[6.242,-33.861]],"c":true},"ix":2},"nm":"Path 1","mn":"ADBE Vector Shape - Group","hd":false},{"ty":"fl","c":{"a":0,"k":[0.949019667682,0.917647118662,0.854902020623,1],"ix":4},"o":{"a":0,"k":100,"ix":5},"r":1,"bm":0,"nm":"Fill 1","mn":"ADBE Vector Graphic - Fill","hd":false},{"ty":"tr","p":{"a":0,"k":[354.35,250.803],"ix":2},"a":{"a":0,"k":[0,0],"ix":1},"s":{"a":0,"k":[100,100],"ix":3},"r":{"a":0,"k":0,"ix":6},"o":{"a":0,"k":100,"ix":7},"sk":{"a":0,"k":0,"ix":4},"sa":{"a":0,"k":0,"ix":5},"nm":"Transform"}],"nm":"Group 12","np":2,"cix":2,"bm":0,"ix":12,"mn":"ADBE Vector Group","hd":false},{"ty":"gr","it":[{"ind":0,"ty":"sh","ix":1,"ks":{"a":0,"k":{"i":[[0,0],[0,0],[0,0],[0,0],[-0.352,-0.427],[0,0]],"o":[[0,0],[0,0],[0,0],[0.352,-0.427],[0,0],[0,0]],"v":[[6.242,41.042],[-6.242,41.042],[-6.242,-33.861],[-0.68,-40.615],[0.68,-40.615],[6.242,-33.861]],"c":true},"ix":2},"nm":"Path 1","mn":"ADBE Vector Shape - Group","hd":false},{"ty":"fl","c":{"a":0,"k":[0.949019667682,0.917647118662,0.854902020623,1],"ix":4},"o":{"a":0,"k":100,"ix":5},"r":1,"bm":0,"nm":"Fill 1","mn":"ADBE Vector Graphic - Fill","hd":false},{"ty":"tr","p":{"a":0,"k":[380.566,250.803],"ix":2},"a":{"a":0,"k":[0,0],"ix":1},"s":{"a":0,"k":[100,100],"ix":3},"r":{"a":0,"k":0,"ix":6},"o":{"a":0,"k":100,"ix":7},"sk":{"a":0,"k":0,"ix":4},"sa":{"a":0,"k":0,"ix":5},"nm":"Transform"}],"nm":"Group 13","np":2,"cix":2,"bm":0,"ix":13,"mn":"ADBE Vector Group","hd":false},{"ty":"gr","it":[{"ind":0,"ty":"sh","ix":1,"ks":{"a":0,"k":{"i":[[0,0],[0,0],[0,0],[0,0],[-0.352,-0.427],[0,0]],"o":[[0,0],[0,0],[0,0],[0.352,-0.427],[0,0],[0,0]],"v":[[6.242,41.042],[-6.242,41.042],[-6.242,-33.861],[-0.68,-40.615],[0.68,-40.615],[6.242,-33.861]],"c":true},"ix":2},"nm":"Path 1","mn":"ADBE Vector Shape - Group","hd":false},{"ty":"fl","c":{"a":0,"k":[0.949019667682,0.917647118662,0.854902020623,1],"ix":4},"o":{"a":0,"k":100,"ix":5},"r":1,"bm":0,"nm":"Fill 1","mn":"ADBE Vector Graphic - Fill","hd":false},{"ty":"tr","p":{"a":0,"k":[301.918,250.803],"ix":2},"a":{"a":0,"k":[0,0],"ix":1},"s":{"a":0,"k":[100,100],"ix":3},"r":{"a":0,"k":0,"ix":6},"o":{"a":0,"k":100,"ix":7},"sk":{"a":0,"k":0,"ix":4},"sa":{"a":0,"k":0,"ix":5},"nm":"Transform"}],"nm":"Group 14","np":2,"cix":2,"bm":0,"ix":14,"mn":"ADBE Vector Group","hd":false},{"ty":"gr","it":[{"ind":0,"ty":"sh","ix":1,"ks":{"a":0,"k":{"i":[[0,0],[0,0],[0,0],[0,0],[-0.352,-0.427],[0,0]],"o":[[0,0],[0,0],[0,0],[0.352,-0.427],[0,0],[0,0]],"v":[[6.242,41.042],[-6.242,41.042],[-6.242,-33.861],[-0.68,-40.615],[0.68,-40.615],[6.242,-33.861]],"c":true},"ix":2},"nm":"Path 1","mn":"ADBE Vector Shape - Group","hd":false},{"ty":"fl","c":{"a":0,"k":[0.949019667682,0.917647118662,0.854902020623,1],"ix":4},"o":{"a":0,"k":100,"ix":5},"r":1,"bm":0,"nm":"Fill 1","mn":"ADBE Vector Graphic - Fill","hd":false},{"ty":"tr","p":{"a":0,"k":[328.134,250.803],"ix":2},"a":{"a":0,"k":[0,0],"ix":1},"s":{"a":0,"k":[100,100],"ix":3},"r":{"a":0,"k":0,"ix":6},"o":{"a":0,"k":100,"ix":7},"sk":{"a":0,"k":0,"ix":4},"sa":{"a":0,"k":0,"ix":5},"nm":"Transform"}],"nm":"Group 15","np":2,"cix":2,"bm":0,"ix":15,"mn":"ADBE Vector Group","hd":false}],"ip":0,"op":118,"st":0,"bm":0}]}],"layers":[{"ddd":0,"ind":1,"ty":4,"nm":"Right Wheel Outlines","sr":1,"ks":{"o":{"a":0,"k":100,"ix":11},"r":{"a":1,"k":[{"i":{"x":[0.833],"y":[0.833]},"o":{"x":[0.167],"y":[0.167]},"t":0,"s":[0]},{"t":120,"s":[510]}],"ix":10},"p":{"a":0,"k":[283.25,267.75,0],"ix":2,"l":2},"a":{"a":0,"k":[283.25,267.75,0],"ix":1,"l":2},"s":{"a":0,"k":[100,100,100],"ix":6,"l":2}},"ao":0,"shapes":[{"ty":"gr","it":[{"ind":0,"ty":"sh","ix":1,"ks":{"a":0,"k":{"i":[[0,-2.297],[2.297,0],[0,2.297],[-2.298,0]],"o":[[0,2.297],[-2.298,0],[0,-2.297],[2.297,0]],"v":[[4.16,0],[0.001,4.159],[-4.159,0],[0.001,-4.159]],"c":true},"ix":2},"nm":"Path 1","mn":"ADBE Vector Shape - Group","hd":false},{"ty":"fl","c":{"a":0,"k":[0.937254961799,0.756862804936,0.376470618154,1],"ix":4},"o":{"a":0,"k":100,"ix":5},"r":1,"bm":0,"nm":"Fill 1","mn":"ADBE Vector Graphic - Fill","hd":false},{"ty":"tr","p":{"a":0,"k":[283.386,267.742],"ix":2},"a":{"a":0,"k":[0,0],"ix":1},"s":{"a":0,"k":[100,100],"ix":3},"r":{"a":0,"k":0,"ix":6},"o":{"a":0,"k":100,"ix":7},"sk":{"a":0,"k":0,"ix":4},"sa":{"a":0,"k":0,"ix":5},"nm":"Transform"}],"nm":"Group 1","np":2,"cix":2,"bm":0,"ix":1,"mn":"ADBE Vector Group","hd":false},{"ty":"gr","it":[{"ind":0,"ty":"sh","ix":1,"ks":{"a":0,"k":{"i":[[0,-6.568],[6.568,0],[0,6.568],[-6.568,0]],"o":[[0,6.568],[-6.568,0],[0,-6.568],[6.568,0]],"v":[[11.892,0],[0,11.892],[-11.892,0],[0,-11.892]],"c":true},"ix":2},"nm":"Path 1","mn":"ADBE Vector Shape - Group","hd":false},{"ty":"fl","c":{"a":0,"k":[0.972549079446,0.886274569642,0.419607873056,1],"ix":4},"o":{"a":0,"k":100,"ix":5},"r":1,"bm":0,"nm":"Fill 1","mn":"ADBE Vector Graphic - Fill","hd":false},{"ty":"tr","p":{"a":0,"k":[283.387,267.742],"ix":2},"a":{"a":0,"k":[0,0],"ix":1},"s":{"a":0,"k":[100,100],"ix":3},"r":{"a":0,"k":0,"ix":6},"o":{"a":0,"k":100,"ix":7},"sk":{"a":0,"k":0,"ix":4},"sa":{"a":0,"k":0,"ix":5},"nm":"Transform"}],"nm":"Group 2","np":2,"cix":2,"bm":0,"ix":2,"mn":"ADBE Vector Group","hd":false},{"ty":"gr","it":[{"ind":0,"ty":"sh","ix":1,"ks":{"a":0,"k":{"i":[[0,-8.23],[8.231,0],[0,8.23],[-8.23,0]],"o":[[0,8.23],[-8.23,0],[0,-8.23],[8.231,0]],"v":[[14.902,0],[-0.001,14.903],[-14.902,0],[-0.001,-14.903]],"c":true},"ix":2},"nm":"Path 1","mn":"ADBE Vector Shape - Group","hd":false},{"ty":"fl","c":{"a":0,"k":[0.941176530427,0.760784373564,0.372549019608,1],"ix":4},"o":{"a":0,"k":100,"ix":5},"r":1,"bm":0,"nm":"Fill 1","mn":"ADBE Vector Graphic - Fill","hd":false},{"ty":"tr","p":{"a":0,"k":[283.387,267.742],"ix":2},"a":{"a":0,"k":[0,0],"ix":1},"s":{"a":0,"k":[100,100],"ix":3},"r":{"a":0,"k":0,"ix":6},"o":{"a":0,"k":100,"ix":7},"sk":{"a":0,"k":0,"ix":4},"sa":{"a":0,"k":0,"ix":5},"nm":"Transform"}],"nm":"Group 3","np":2,"cix":2,"bm":0,"ix":3,"mn":"ADBE Vector Group","hd":false},{"ty":"gr","it":[{"ind":0,"ty":"sh","ix":1,"ks":{"a":0,"k":{"i":[[0,0],[0,0],[0,0],[0,0],[0,0],[0,0],[0,0],[0,0],[0,0],[0,0],[0,0],[0,0],[0,0],[0,0],[0,0],[0,0],[0,0],[0,0],[0,0],[0,0],[0,0],[0,0],[0,0],[0,0],[0,0],[0,0],[0,0],[0,0],[0,0],[0,0],[0,0],[0,0],[0,0],[0,0],[0,0],[0,0],[0,0],[0,0]],"o":[[0,0],[0,0],[0,0],[0,0],[0,0],[0,0],[0,0],[0,0],[0,0],[0,0],[0,0],[0,0],[0,0],[0,0],[0,0],[0,0],[0,0],[0,0],[0,0],[0,0],[0,0],[0,0],[0,0],[0,0],[0,0],[0,0],[0,0],[0,0],[0,0],[0,0],[0,0],[0,0],[0,0],[0,0],[0,0],[0,0],[0,0],[0,0]],"v":[[24.428,19.048],[20.086,21.903],[16.906,26.014],[11.872,27.305],[7.53,30.16],[2.349,29.746],[-2.685,31.037],[-7.449,28.963],[-12.63,28.549],[-16.465,25.041],[-21.229,22.968],[-23.716,18.404],[-27.551,14.896],[-28.422,9.772],[-30.909,5.209],[-30.068,0.081],[-30.939,-5.043],[-28.479,-9.621],[-27.639,-14.749],[-23.826,-18.28],[-21.366,-22.858],[-16.612,-24.96],[-12.799,-28.491],[-7.621,-28.936],[-2.868,-31.037],[2.173,-29.776],[7.352,-30.221],[11.711,-27.391],[16.751,-26.131],[19.956,-22.039],[24.315,-19.209],[26.017,-14.299],[29.221,-10.207],[29.237,-5.01],[30.939,-0.1],[29.266,4.82],[29.281,10.017],[26.102,14.128]],"c":true},"ix":2},"nm":"Path 1","mn":"ADBE Vector Shape - Group","hd":false},{"ty":"fl","c":{"a":0,"k":[0.203921583587,0.219607858097,0.20000001496,1],"ix":4},"o":{"a":0,"k":100,"ix":5},"r":1,"bm":0,"nm":"Fill 1","mn":"ADBE Vector Graphic - Fill","hd":false},{"ty":"tr","p":{"a":0,"k":[283.386,267.742],"ix":2},"a":{"a":0,"k":[0,0],"ix":1},"s":{"a":0,"k":[100,100],"ix":3},"r":{"a":0,"k":0,"ix":6},"o":{"a":0,"k":100,"ix":7},"sk":{"a":0,"k":0,"ix":4},"sa":{"a":0,"k":0,"ix":5},"nm":"Transform"}],"nm":"Group 4","np":2,"cix":2,"bm":0,"ix":4,"mn":"ADBE Vector Group","hd":false}],"ip":0,"op":115,"st":0,"bm":0},{"ddd":0,"ind":2,"ty":4,"nm":"Left wheel Outlines","sr":1,"ks":{"o":{"a":0,"k":100,"ix":11},"r":{"a":1,"k":[{"i":{"x":[0.833],"y":[0.833]},"o":{"x":[0.167],"y":[0.167]},"t":0,"s":[0]},{"t":120,"s":[359]}],"ix":10},"p":{"a":0,"k":[167.938,254.438,0],"ix":2,"l":2},"a":{"a":0,"k":[167.938,254.438,0],"ix":1,"l":2},"s":{"a":0,"k":[100,100,100],"ix":6,"l":2}},"ao":0,"shapes":[{"ty":"gr","it":[{"ind":0,"ty":"sh","ix":1,"ks":{"a":0,"k":{"i":[[0,-3.774],[3.774,0],[0,3.774],[-3.773,0]],"o":[[0,3.774],[-3.773,0],[0,-3.774],[3.774,0]],"v":[[6.833,0],[0,6.833],[-6.832,0],[0,-6.833]],"c":true},"ix":2},"nm":"Path 1","mn":"ADBE Vector Shape - Group","hd":false},{"ty":"fl","c":{"a":0,"k":[0.937254961799,0.756862804936,0.376470618154,1],"ix":4},"o":{"a":0,"k":100,"ix":5},"r":1,"bm":0,"nm":"Fill 1","mn":"ADBE Vector Graphic - Fill","hd":false},{"ty":"tr","p":{"a":0,"k":[168.086,254.293],"ix":2},"a":{"a":0,"k":[0,0],"ix":1},"s":{"a":0,"k":[100,100],"ix":3},"r":{"a":0,"k":0,"ix":6},"o":{"a":0,"k":100,"ix":7},"sk":{"a":0,"k":0,"ix":4},"sa":{"a":0,"k":0,"ix":5},"nm":"Transform"}],"nm":"Group 1","np":2,"cix":2,"bm":0,"ix":1,"mn":"ADBE Vector Group","hd":false},{"ty":"gr","it":[{"ind":0,"ty":"sh","ix":1,"ks":{"a":0,"k":{"i":[[0,-10.794],[10.794,0],[0,10.794],[-10.794,0]],"o":[[0,10.794],[-10.794,0],[0,-10.794],[10.794,0]],"v":[[19.545,0],[0,19.545],[-19.545,0],[0,-19.545]],"c":true},"ix":2},"nm":"Path 1","mn":"ADBE Vector Shape - Group","hd":false},{"ty":"fl","c":{"a":0,"k":[0.972549079446,0.886274569642,0.419607873056,1],"ix":4},"o":{"a":0,"k":100,"ix":5},"r":1,"bm":0,"nm":"Fill 1","mn":"ADBE Vector Graphic - Fill","hd":false},{"ty":"tr","p":{"a":0,"k":[168.086,254.293],"ix":2},"a":{"a":0,"k":[0,0],"ix":1},"s":{"a":0,"k":[100,100],"ix":3},"r":{"a":0,"k":0,"ix":6},"o":{"a":0,"k":100,"ix":7},"sk":{"a":0,"k":0,"ix":4},"sa":{"a":0,"k":0,"ix":5},"nm":"Transform"}],"nm":"Group 2","np":2,"cix":2,"bm":0,"ix":2,"mn":"ADBE Vector Group","hd":false},{"ty":"gr","it":[{"ind":0,"ty":"sh","ix":1,"ks":{"a":0,"k":{"i":[[0,-13.52],[13.52,0],[0,13.52],[-13.52,0]],"o":[[0,13.52],[-13.52,0],[0,-13.52],[13.52,0]],"v":[[24.48,0],[0.001,24.48],[-24.48,0],[0.001,-24.48]],"c":true},"ix":2},"nm":"Path 1","mn":"ADBE Vector Shape - Group","hd":false},{"ty":"fl","c":{"a":0,"k":[0.941176530427,0.760784373564,0.372549019608,1],"ix":4},"o":{"a":0,"k":100,"ix":5},"r":1,"bm":0,"nm":"Fill 1","mn":"ADBE Vector Graphic - Fill","hd":false},{"ty":"tr","p":{"a":0,"k":[168.086,254.293],"ix":2},"a":{"a":0,"k":[0,0],"ix":1},"s":{"a":0,"k":[100,100],"ix":3},"r":{"a":0,"k":0,"ix":6},"o":{"a":0,"k":100,"ix":7},"sk":{"a":0,"k":0,"ix":4},"sa":{"a":0,"k":0,"ix":5},"nm":"Transform"}],"nm":"Group 3","np":2,"cix":2,"bm":0,"ix":3,"mn":"ADBE Vector Group","hd":false},{"ty":"gr","it":[{"ind":0,"ty":"sh","ix":1,"ks":{"a":0,"k":{"i":[[0,0],[0,0],[0,0],[0,0],[0,0],[0,0],[0,0],[0,0],[0,0],[0,0],[0,0],[0,0],[0,0],[0,0],[0,0],[0,0],[0,0],[0,0],[0,0],[0,0],[0,0],[0,0],[0,0],[0,0],[0,0],[0,0],[0,0],[0,0],[0,0],[0,0],[0,0],[0,0],[0,0],[0,0],[0,0],[0,0],[0,0],[0,0]],"o":[[0,0],[0,0],[0,0],[0,0],[0,0],[0,0],[0,0],[0,0],[0,0],[0,0],[0,0],[0,0],[0,0],[0,0],[0,0],[0,0],[0,0],[0,0],[0,0],[0,0],[0,0],[0,0],[0,0],[0,0],[0,0],[0,0],[0,0],[0,0],[0,0],[0,0],[0,0],[0,0],[0,0],[0,0],[0,0],[0,0],[0,0],[0,0]],"v":[[35.014,27.302],[28.79,31.395],[24.232,37.285],[17.017,39.135],[10.792,43.229],[3.368,42.635],[-3.847,44.486],[-10.678,41.513],[-18.104,40.921],[-23.598,35.891],[-30.428,32.919],[-33.993,26.378],[-39.488,21.35],[-40.736,14.007],[-44.301,7.466],[-43.096,0.115],[-44.344,-7.229],[-40.818,-13.79],[-39.614,-21.141],[-34.148,-26.202],[-30.623,-32.764],[-23.811,-35.775],[-18.346,-40.837],[-10.923,-41.474],[-4.111,-44.486],[3.115,-42.678],[10.536,-43.315],[16.785,-39.26],[24.01,-37.453],[28.604,-31.589],[34.852,-27.533],[37.29,-20.495],[41.883,-14.63],[41.906,-7.182],[44.344,-0.143],[41.947,6.909],[41.969,14.357],[37.411,20.25]],"c":true},"ix":2},"nm":"Path 1","mn":"ADBE Vector Shape - Group","hd":false},{"ty":"fl","c":{"a":0,"k":[0.203921583587,0.219607858097,0.20000001496,1],"ix":4},"o":{"a":0,"k":100,"ix":5},"r":1,"bm":0,"nm":"Fill 1","mn":"ADBE Vector Graphic - Fill","hd":false},{"ty":"tr","p":{"a":0,"k":[168.086,254.294],"ix":2},"a":{"a":0,"k":[0,0],"ix":1},"s":{"a":0,"k":[100,100],"ix":3},"r":{"a":0,"k":0,"ix":6},"o":{"a":0,"k":100,"ix":7},"sk":{"a":0,"k":0,"ix":4},"sa":{"a":0,"k":0,"ix":5},"nm":"Transform"}],"nm":"Group 4","np":2,"cix":2,"bm":0,"ix":4,"mn":"ADBE Vector Group","hd":false}],"ip":0,"op":115,"st":0,"bm":0},{"ddd":0,"ind":3,"ty":4,"nm":"Cloud Outlines 4","sr":1,"ks":{"o":{"a":1,"k":[{"i":{"x":[0.833],"y":[0.833]},"o":{"x":[0.167],"y":[0.167]},"t":98,"s":[100]},{"t":108,"s":[0]}],"ix":11},"r":{"a":0,"k":0,"ix":10},"p":{"a":1,"k":[{"i":{"x":0.833,"y":0.833},"o":{"x":0.167,"y":0.167},"t":92,"s":[304.611,165.639,0],"to":[-0.024,-0.251,0],"ti":[-20.273,-0.62,0]},{"i":{"x":0.833,"y":0.833},"o":{"x":0.167,"y":0.167},"t":97,"s":[325.423,159.014,0],"to":[0.072,0.002,0],"ti":[0.242,0.222,0]},{"i":{"x":0.833,"y":0.833},"o":{"x":0.167,"y":0.167},"t":98,"s":[325.5,159.031,0],"to":[-16.634,-15.258,0],"ti":[56.873,-5.922,0]},{"t":115,"s":[196.5,124,0]}],"ix":2,"l":2},"a":{"a":0,"k":[302,160,0],"ix":1,"l":2},"s":{"a":0,"k":[100,100,100],"ix":6,"l":2}},"ao":0,"shapes":[{"ty":"gr","it":[{"ind":0,"ty":"sh","ix":1,"ks":{"a":0,"k":{"i":[[3.785,0],[0.413,-0.064],[3.765,0],[1.098,-0.343],[2.473,0],[1.215,-3.412],[0.687,0],[0,-3.107],[-3.766,0],[-0.345,0.044],[-3.929,0],[-1.798,1.451],[-1.056,0],[-1.815,2.038],[-1.272,0],[0,3.124]],"o":[[-0.435,0],[-1.696,-2.543],[-1.245,0],[-1.743,-1.23],[-4.529,0],[-0.625,-0.156],[-3.766,0],[0,3.107],[0.36,0],[1.625,2.725],[2.713,0],[0.955,0.251],[3.299,0],[1.02,0.498],[3.785,0],[0,-3.123]],"v":[[15.697,-5.093],[14.426,-4.987],[5.725,-9.272],[2.203,-8.718],[-4.246,-10.718],[-13.771,-4.799],[-15.733,-5.064],[-22.551,0.562],[-15.733,6.188],[-14.681,6.101],[-5.762,10.718],[1.203,8.367],[4.211,8.79],[12.228,5.414],[15.697,6.218],[22.551,0.562]],"c":true},"ix":2},"nm":"Path 1","mn":"ADBE Vector Shape - Group","hd":false},{"ty":"fl","c":{"a":0,"k":[0.850980451995,0.886274569642,0.886274569642,1],"ix":4},"o":{"a":0,"k":100,"ix":5},"r":1,"bm":0,"nm":"Fill 1","mn":"ADBE Vector Graphic - Fill","hd":false},{"ty":"tr","p":{"a":0,"k":[302.003,161.08],"ix":2},"a":{"a":0,"k":[0,0],"ix":1},"s":{"a":0,"k":[100,100],"ix":3},"r":{"a":0,"k":0,"ix":6},"o":{"a":0,"k":100,"ix":7},"sk":{"a":0,"k":0,"ix":4},"sa":{"a":0,"k":0,"ix":5},"nm":"Transform"}],"nm":"Group 1","np":2,"cix":2,"bm":0,"ix":1,"mn":"ADBE Vector Group","hd":false}],"ip":92,"op":115,"st":64,"bm":0},{"ddd":0,"ind":4,"ty":4,"nm":"Cloud Outlines 3","sr":1,"ks":{"o":{"a":1,"k":[{"i":{"x":[0.833],"y":[0.833]},"o":{"x":[0.167],"y":[0.167]},"t":71,"s":[100]},{"t":81,"s":[0]}],"ix":11},"r":{"a":0,"k":0,"ix":10},"p":{"a":1,"k":[{"i":{"x":0.833,"y":0.833},"o":{"x":0.167,"y":0.167},"t":65,"s":[304.611,165.639,0],"to":[-0.024,-0.251,0],"ti":[-20.273,-0.62,0]},{"i":{"x":0.833,"y":0.833},"o":{"x":0.167,"y":0.167},"t":70,"s":[325.423,159.014,0],"to":[0.072,0.002,0],"ti":[0.242,0.222,0]},{"i":{"x":0.833,"y":0.833},"o":{"x":0.167,"y":0.167},"t":71,"s":[325.5,159.031,0],"to":[-16.634,-15.258,0],"ti":[56.873,-5.922,0]},{"t":88,"s":[196.5,124,0]}],"ix":2,"l":2},"a":{"a":0,"k":[302,160,0],"ix":1,"l":2},"s":{"a":0,"k":[100,100,100],"ix":6,"l":2}},"ao":0,"shapes":[{"ty":"gr","it":[{"ind":0,"ty":"sh","ix":1,"ks":{"a":0,"k":{"i":[[3.785,0],[0.413,-0.064],[3.765,0],[1.098,-0.343],[2.473,0],[1.215,-3.412],[0.687,0],[0,-3.107],[-3.766,0],[-0.345,0.044],[-3.929,0],[-1.798,1.451],[-1.056,0],[-1.815,2.038],[-1.272,0],[0,3.124]],"o":[[-0.435,0],[-1.696,-2.543],[-1.245,0],[-1.743,-1.23],[-4.529,0],[-0.625,-0.156],[-3.766,0],[0,3.107],[0.36,0],[1.625,2.725],[2.713,0],[0.955,0.251],[3.299,0],[1.02,0.498],[3.785,0],[0,-3.123]],"v":[[15.697,-5.093],[14.426,-4.987],[5.725,-9.272],[2.203,-8.718],[-4.246,-10.718],[-13.771,-4.799],[-15.733,-5.064],[-22.551,0.562],[-15.733,6.188],[-14.681,6.101],[-5.762,10.718],[1.203,8.367],[4.211,8.79],[12.228,5.414],[15.697,6.218],[22.551,0.562]],"c":true},"ix":2},"nm":"Path 1","mn":"ADBE Vector Shape - Group","hd":false},{"ty":"fl","c":{"a":0,"k":[0.850980451995,0.886274569642,0.886274569642,1],"ix":4},"o":{"a":0,"k":100,"ix":5},"r":1,"bm":0,"nm":"Fill 1","mn":"ADBE Vector Graphic - Fill","hd":false},{"ty":"tr","p":{"a":0,"k":[302.003,161.08],"ix":2},"a":{"a":0,"k":[0,0],"ix":1},"s":{"a":0,"k":[100,100],"ix":3},"r":{"a":0,"k":0,"ix":6},"o":{"a":0,"k":100,"ix":7},"sk":{"a":0,"k":0,"ix":4},"sa":{"a":0,"k":0,"ix":5},"nm":"Transform"}],"nm":"Group 1","np":2,"cix":2,"bm":0,"ix":1,"mn":"ADBE Vector Group","hd":false}],"ip":65,"op":88,"st":37,"bm":0},{"ddd":0,"ind":5,"ty":4,"nm":"Cloud Outlines 2","sr":1,"ks":{"o":{"a":1,"k":[{"i":{"x":[0.833],"y":[0.833]},"o":{"x":[0.167],"y":[0.167]},"t":44,"s":[100]},{"t":54,"s":[0]}],"ix":11},"r":{"a":0,"k":0,"ix":10},"p":{"a":1,"k":[{"i":{"x":0.833,"y":0.833},"o":{"x":0.167,"y":0.167},"t":38,"s":[304.611,165.639,0],"to":[-0.024,-0.251,0],"ti":[-20.273,-0.62,0]},{"i":{"x":0.833,"y":0.833},"o":{"x":0.167,"y":0.167},"t":43,"s":[325.423,159.014,0],"to":[0.072,0.002,0],"ti":[0.242,0.222,0]},{"i":{"x":0.833,"y":0.833},"o":{"x":0.167,"y":0.167},"t":44,"s":[325.5,159.031,0],"to":[-16.634,-15.258,0],"ti":[56.873,-5.922,0]},{"t":61,"s":[196.5,124,0]}],"ix":2,"l":2},"a":{"a":0,"k":[302,160,0],"ix":1,"l":2},"s":{"a":0,"k":[100,100,100],"ix":6,"l":2}},"ao":0,"shapes":[{"ty":"gr","it":[{"ind":0,"ty":"sh","ix":1,"ks":{"a":0,"k":{"i":[[3.785,0],[0.413,-0.064],[3.765,0],[1.098,-0.343],[2.473,0],[1.215,-3.412],[0.687,0],[0,-3.107],[-3.766,0],[-0.345,0.044],[-3.929,0],[-1.798,1.451],[-1.056,0],[-1.815,2.038],[-1.272,0],[0,3.124]],"o":[[-0.435,0],[-1.696,-2.543],[-1.245,0],[-1.743,-1.23],[-4.529,0],[-0.625,-0.156],[-3.766,0],[0,3.107],[0.36,0],[1.625,2.725],[2.713,0],[0.955,0.251],[3.299,0],[1.02,0.498],[3.785,0],[0,-3.123]],"v":[[15.697,-5.093],[14.426,-4.987],[5.725,-9.272],[2.203,-8.718],[-4.246,-10.718],[-13.771,-4.799],[-15.733,-5.064],[-22.551,0.562],[-15.733,6.188],[-14.681,6.101],[-5.762,10.718],[1.203,8.367],[4.211,8.79],[12.228,5.414],[15.697,6.218],[22.551,0.562]],"c":true},"ix":2},"nm":"Path 1","mn":"ADBE Vector Shape - Group","hd":false},{"ty":"fl","c":{"a":0,"k":[0.850980451995,0.886274569642,0.886274569642,1],"ix":4},"o":{"a":0,"k":100,"ix":5},"r":1,"bm":0,"nm":"Fill 1","mn":"ADBE Vector Graphic - Fill","hd":false},{"ty":"tr","p":{"a":0,"k":[302.003,161.08],"ix":2},"a":{"a":0,"k":[0,0],"ix":1},"s":{"a":0,"k":[100,100],"ix":3},"r":{"a":0,"k":0,"ix":6},"o":{"a":0,"k":100,"ix":7},"sk":{"a":0,"k":0,"ix":4},"sa":{"a":0,"k":0,"ix":5},"nm":"Transform"}],"nm":"Group 1","np":2,"cix":2,"bm":0,"ix":1,"mn":"ADBE Vector Group","hd":false}],"ip":38,"op":61,"st":10,"bm":0},{"ddd":0,"ind":6,"ty":4,"nm":"Cloud Outlines","sr":1,"ks":{"o":{"a":1,"k":[{"i":{"x":[0.833],"y":[0.833]},"o":{"x":[0.167],"y":[0.167]},"t":17,"s":[100]},{"t":27,"s":[0]}],"ix":11},"r":{"a":0,"k":0,"ix":10},"p":{"a":1,"k":[{"i":{"x":0.833,"y":0.833},"o":{"x":0.167,"y":0.167},"t":11,"s":[304.611,165.639,0],"to":[-0.024,-0.251,0],"ti":[-20.273,-0.62,0]},{"i":{"x":0.833,"y":0.833},"o":{"x":0.167,"y":0.167},"t":16,"s":[325.423,159.014,0],"to":[0.072,0.002,0],"ti":[0.242,0.222,0]},{"i":{"x":0.833,"y":0.833},"o":{"x":0.167,"y":0.167},"t":17,"s":[325.5,159.031,0],"to":[-16.634,-15.258,0],"ti":[56.873,-5.922,0]},{"t":34,"s":[196.5,124,0]}],"ix":2,"l":2},"a":{"a":0,"k":[302,160,0],"ix":1,"l":2},"s":{"a":0,"k":[100,100,100],"ix":6,"l":2}},"ao":0,"shapes":[{"ty":"gr","it":[{"ind":0,"ty":"sh","ix":1,"ks":{"a":0,"k":{"i":[[3.785,0],[0.413,-0.064],[3.765,0],[1.098,-0.343],[2.473,0],[1.215,-3.412],[0.687,0],[0,-3.107],[-3.766,0],[-0.345,0.044],[-3.929,0],[-1.798,1.451],[-1.056,0],[-1.815,2.038],[-1.272,0],[0,3.124]],"o":[[-0.435,0],[-1.696,-2.543],[-1.245,0],[-1.743,-1.23],[-4.529,0],[-0.625,-0.156],[-3.766,0],[0,3.107],[0.36,0],[1.625,2.725],[2.713,0],[0.955,0.251],[3.299,0],[1.02,0.498],[3.785,0],[0,-3.123]],"v":[[15.697,-5.093],[14.426,-4.987],[5.725,-9.272],[2.203,-8.718],[-4.246,-10.718],[-13.771,-4.799],[-15.733,-5.064],[-22.551,0.562],[-15.733,6.188],[-14.681,6.101],[-5.762,10.718],[1.203,8.367],[4.211,8.79],[12.228,5.414],[15.697,6.218],[22.551,0.562]],"c":true},"ix":2},"nm":"Path 1","mn":"ADBE Vector Shape - Group","hd":false},{"ty":"fl","c":{"a":0,"k":[0.850980451995,0.886274569642,0.886274569642,1],"ix":4},"o":{"a":0,"k":100,"ix":5},"r":1,"bm":0,"nm":"Fill 1","mn":"ADBE Vector Graphic - Fill","hd":false},{"ty":"tr","p":{"a":0,"k":[302.003,161.08],"ix":2},"a":{"a":0,"k":[0,0],"ix":1},"s":{"a":0,"k":[100,100],"ix":3},"r":{"a":0,"k":0,"ix":6},"o":{"a":0,"k":100,"ix":7},"sk":{"a":0,"k":0,"ix":4},"sa":{"a":0,"k":0,"ix":5},"nm":"Transform"}],"nm":"Group 1","np":2,"cix":2,"bm":0,"ix":1,"mn":"ADBE Vector Group","hd":false}],"ip":11,"op":34,"st":-17,"bm":0},{"ddd":0,"ind":7,"ty":4,"nm":"Body Outlines","sr":1,"ks":{"o":{"a":0,"k":100,"ix":11},"r":{"a":0,"k":0,"ix":10},"p":{"a":1,"k":[{"i":{"x":0.667,"y":1},"o":{"x":0.333,"y":0},"t":0,"s":[225,225,0],"to":[0,-0.833,0],"ti":[0,0,0]},{"i":{"x":0.667,"y":1},"o":{"x":0.333,"y":0},"t":5,"s":[225,220,0],"to":[0,0,0],"ti":[0,-0.833,0]},{"i":{"x":0.667,"y":0.667},"o":{"x":0.333,"y":0.333},"t":10,"s":[225,225,0],"to":[0,0,0],"ti":[0,0,0]},{"i":{"x":0.667,"y":1},"o":{"x":0.333,"y":0},"t":15,"s":[225,225,0],"to":[0,-0.833,0],"ti":[0,0,0]},{"i":{"x":0.667,"y":1},"o":{"x":0.333,"y":0},"t":20,"s":[225,220,0],"to":[0,0,0],"ti":[0,-0.833,0]},{"i":{"x":0.667,"y":0.667},"o":{"x":0.333,"y":0.333},"t":25,"s":[225,225,0],"to":[0,0,0],"ti":[0,0,0]},{"i":{"x":0.667,"y":1},"o":{"x":0.333,"y":0},"t":30,"s":[225,225,0],"to":[0,-0.833,0],"ti":[0,0,0]},{"i":{"x":0.667,"y":1},"o":{"x":0.333,"y":0},"t":35,"s":[225,220,0],"to":[0,0,0],"ti":[0,-0.833,0]},{"i":{"x":0.667,"y":0.667},"o":{"x":0.333,"y":0.333},"t":40,"s":[225,225,0],"to":[0,0,0],"ti":[0,0,0]},{"i":{"x":0.667,"y":1},"o":{"x":0.333,"y":0},"t":45,"s":[225,225,0],"to":[0,-0.833,0],"ti":[0,0,0]},{"i":{"x":0.667,"y":1},"o":{"x":0.333,"y":0},"t":50,"s":[225,220,0],"to":[0,0,0],"ti":[0,-0.833,0]},{"i":{"x":0.667,"y":0.667},"o":{"x":0.333,"y":0.333},"t":55,"s":[225,225,0],"to":[0,0,0],"ti":[0,0,0]},{"i":{"x":0.667,"y":1},"o":{"x":0.333,"y":0},"t":60,"s":[225,225,0],"to":[0,-0.833,0],"ti":[0,0,0]},{"i":{"x":0.667,"y":1},"o":{"x":0.333,"y":0},"t":65,"s":[225,220,0],"to":[0,0,0],"ti":[0,-0.833,0]},{"i":{"x":0.667,"y":0.667},"o":{"x":0.333,"y":0.333},"t":70,"s":[225,225,0],"to":[0,0,0],"ti":[0,0,0]},{"i":{"x":0.667,"y":1},"o":{"x":0.333,"y":0},"t":75,"s":[225,225,0],"to":[0,-0.833,0],"ti":[0,0,0]},{"i":{"x":0.667,"y":1},"o":{"x":0.333,"y":0},"t":80,"s":[225,220,0],"to":[0,0,0],"ti":[0,-0.833,0]},{"i":{"x":0.667,"y":0.667},"o":{"x":0.333,"y":0.333},"t":85,"s":[225,225,0],"to":[0,0,0],"ti":[0,0,0]},{"i":{"x":0.667,"y":1},"o":{"x":0.333,"y":0},"t":90,"s":[225,225,0],"to":[0,-0.833,0],"ti":[0,0,0]},{"i":{"x":0.667,"y":1},"o":{"x":0.333,"y":0},"t":95,"s":[225,220,0],"to":[0,0,0],"ti":[0,0.083,0]},{"i":{"x":0.667,"y":1},"o":{"x":0.333,"y":0},"t":100,"s":[225,225,0],"to":[0,-0.055,0],"ti":[-0.057,-0.215,0]},{"i":{"x":0.667,"y":1},"o":{"x":0.333,"y":0},"t":105,"s":[225,225,0],"to":[0.096,0.359,0],"ti":[0,0,0]},{"i":{"x":0.667,"y":1},"o":{"x":0.333,"y":0},"t":110,"s":[225,220,0],"to":[0,-0.625,0],"ti":[0,-0.833,0]},{"i":{"x":0.667,"y":0.667},"o":{"x":0.333,"y":0.333},"t":115,"s":[225,225,0],"to":[0,0,0],"ti":[0,0,0]},{"t":120,"s":[225,225,0]}],"ix":2,"l":2},"a":{"a":0,"k":[225,225,0],"ix":1,"l":2},"s":{"a":0,"k":[100,100,100],"ix":6,"l":2}},"ao":0,"shapes":[{"ty":"gr","it":[{"ind":0,"ty":"sh","ix":1,"ks":{"a":0,"k":{"i":[[0.321,-0.321],[0,0],[0.321,0.32],[0,0],[-0.32,0.321],[0,0],[-0.32,-0.32],[0,0]],"o":[[0,0],[-0.32,0.32],[0,0],[-0.32,-0.321],[0,0],[0.321,-0.32],[0,0],[0.321,0.321]],"v":[[6.36,4.622],[4.622,6.361],[3.461,6.361],[-6.361,-3.461],[-6.361,-4.622],[-4.623,-6.361],[-3.462,-6.361],[6.36,3.461]],"c":true},"ix":2},"nm":"Path 1","mn":"ADBE Vector Shape - Group","hd":false},{"ty":"fl","c":{"a":0,"k":[0.980392216701,0.984313785329,0.992156922583,1],"ix":4},"o":{"a":0,"k":100,"ix":5},"r":1,"bm":0,"nm":"Fill 1","mn":"ADBE Vector Graphic - Fill","hd":false},{"ty":"tr","p":{"a":0,"k":[207.446,189.833],"ix":2},"a":{"a":0,"k":[0,0],"ix":1},"s":{"a":0,"k":[100,100],"ix":3},"r":{"a":0,"k":0,"ix":6},"o":{"a":0,"k":100,"ix":7},"sk":{"a":0,"k":0,"ix":4},"sa":{"a":0,"k":0,"ix":5},"nm":"Transform"}],"nm":"Group 1","np":2,"cix":2,"bm":0,"ix":1,"mn":"ADBE Vector Group","hd":false},{"ty":"gr","it":[{"ind":0,"ty":"sh","ix":1,"ks":{"a":0,"k":{"i":[[0.321,-0.321],[0,0],[0.321,0.32],[0,0],[-0.321,0.321],[0,0],[-0.321,-0.32],[0,0]],"o":[[0,0],[-0.32,0.32],[0,0],[-0.321,-0.32],[0,0],[0.321,-0.32],[0,0],[0.321,0.321]],"v":[[15.402,13.665],[13.664,15.403],[12.503,15.403],[-15.402,-12.504],[-15.402,-13.665],[-13.665,-15.403],[-12.504,-15.403],[15.402,12.504]],"c":true},"ix":2},"nm":"Path 1","mn":"ADBE Vector Shape - Group","hd":false},{"ty":"fl","c":{"a":0,"k":[0.980392216701,0.984313785329,0.992156922583,1],"ix":4},"o":{"a":0,"k":100,"ix":5},"r":1,"bm":0,"nm":"Fill 1","mn":"ADBE Vector Graphic - Fill","hd":false},{"ty":"tr","p":{"a":0,"k":[200.532,196.746],"ix":2},"a":{"a":0,"k":[0,0],"ix":1},"s":{"a":0,"k":[100,100],"ix":3},"r":{"a":0,"k":0,"ix":6},"o":{"a":0,"k":100,"ix":7},"sk":{"a":0,"k":0,"ix":4},"sa":{"a":0,"k":0,"ix":5},"nm":"Transform"}],"nm":"Group 2","np":2,"cix":2,"bm":0,"ix":2,"mn":"ADBE Vector Group","hd":false},{"ty":"gr","it":[{"ind":0,"ty":"sh","ix":1,"ks":{"a":0,"k":{"i":[[0.524,-0.302],[0,0],[0.302,0.523],[0,0],[-0.523,0.303],[0,0],[-0.302,-0.524],[0,0]],"o":[[0,0],[-0.523,0.303],[0,0],[-0.302,-0.524],[0,0],[0.524,-0.302],[0,0],[0.302,0.523]],"v":[[4.638,4.756],[1.8,6.394],[0.305,5.994],[-5.039,-3.261],[-4.638,-4.757],[-1.8,-6.395],[-0.305,-5.994],[5.039,3.261]],"c":true},"ix":2},"nm":"Path 1","mn":"ADBE Vector Shape - Group","hd":false},{"ty":"fl","c":{"a":0,"k":[0.203921583587,0.219607858097,0.20000001496,1],"ix":4},"o":{"a":0,"k":100,"ix":5},"r":1,"bm":0,"nm":"Fill 1","mn":"ADBE Vector Graphic - Fill","hd":false},{"ty":"tr","p":{"a":0,"k":[264.253,218.155],"ix":2},"a":{"a":0,"k":[0,0],"ix":1},"s":{"a":0,"k":[100,100],"ix":3},"r":{"a":0,"k":0,"ix":6},"o":{"a":0,"k":100,"ix":7},"sk":{"a":0,"k":0,"ix":4},"sa":{"a":0,"k":0,"ix":5},"nm":"Transform"}],"nm":"Group 3","np":2,"cix":2,"bm":0,"ix":3,"mn":"ADBE Vector Group","hd":false},{"ty":"gr","it":[{"ind":0,"ty":"sh","ix":1,"ks":{"a":0,"k":{"i":[[0.524,-0.302],[0,0],[0.302,0.523],[0,0],[-0.523,0.303],[0,0],[-0.302,-0.524],[0,0]],"o":[[0,0],[-0.523,0.303],[0,0],[-0.303,-0.524],[0,0],[0.524,-0.302],[0,0],[0.302,0.523]],"v":[[4.638,4.756],[1.8,6.394],[0.305,5.994],[-5.038,-3.261],[-4.638,-4.757],[-1.8,-6.395],[-0.305,-5.994],[5.039,3.261]],"c":true},"ix":2},"nm":"Path 1","mn":"ADBE Vector Shape - Group","hd":false},{"ty":"fl","c":{"a":0,"k":[0.203921583587,0.219607858097,0.20000001496,1],"ix":4},"o":{"a":0,"k":100,"ix":5},"r":1,"bm":0,"nm":"Fill 1","mn":"ADBE Vector Graphic - Fill","hd":false},{"ty":"tr","p":{"a":0,"k":[255.315,218.155],"ix":2},"a":{"a":0,"k":[0,0],"ix":1},"s":{"a":0,"k":[100,100],"ix":3},"r":{"a":0,"k":0,"ix":6},"o":{"a":0,"k":100,"ix":7},"sk":{"a":0,"k":0,"ix":4},"sa":{"a":0,"k":0,"ix":5},"nm":"Transform"}],"nm":"Group 4","np":2,"cix":2,"bm":0,"ix":4,"mn":"ADBE Vector Group","hd":false},{"ty":"gr","it":[{"ind":0,"ty":"sh","ix":1,"ks":{"a":0,"k":{"i":[[0.524,-0.302],[0,0],[0.302,0.523],[0,0],[-0.523,0.303],[0,0],[-0.302,-0.524],[0,0]],"o":[[0,0],[-0.523,0.303],[0,0],[-0.303,-0.524],[0,0],[0.524,-0.302],[0,0],[0.302,0.523]],"v":[[4.638,4.756],[1.8,6.394],[0.305,5.994],[-5.038,-3.261],[-4.638,-4.757],[-1.8,-6.395],[-0.305,-5.994],[5.039,3.261]],"c":true},"ix":2},"nm":"Path 1","mn":"ADBE Vector Shape - Group","hd":false},{"ty":"fl","c":{"a":0,"k":[0.203921583587,0.219607858097,0.20000001496,1],"ix":4},"o":{"a":0,"k":100,"ix":5},"r":1,"bm":0,"nm":"Fill 1","mn":"ADBE Vector Graphic - Fill","hd":false},{"ty":"tr","p":{"a":0,"k":[246.378,218.155],"ix":2},"a":{"a":0,"k":[0,0],"ix":1},"s":{"a":0,"k":[100,100],"ix":3},"r":{"a":0,"k":0,"ix":6},"o":{"a":0,"k":100,"ix":7},"sk":{"a":0,"k":0,"ix":4},"sa":{"a":0,"k":0,"ix":5},"nm":"Transform"}],"nm":"Group 5","np":2,"cix":2,"bm":0,"ix":5,"mn":"ADBE Vector Group","hd":false},{"ty":"gr","it":[{"ind":0,"ty":"sh","ix":1,"ks":{"a":0,"k":{"i":[[0,0],[0,0],[0,0],[0,0]],"o":[[0,0],[0,0],[0,0],[0,0]],"v":[[10.334,3.416],[-10.333,3.416],[-10.333,-3.417],[10.334,-3.417]],"c":true},"ix":2},"nm":"Path 1","mn":"ADBE Vector Shape - Group","hd":false},{"ty":"fl","c":{"a":0,"k":[0.203921583587,0.219607858097,0.20000001496,1],"ix":4},"o":{"a":0,"k":100,"ix":5},"r":1,"bm":0,"nm":"Fill 1","mn":"ADBE Vector Graphic - Fill","hd":false},{"ty":"tr","p":{"a":0,"k":[222.764,231.254],"ix":2},"a":{"a":0,"k":[0,0],"ix":1},"s":{"a":0,"k":[100,100],"ix":3},"r":{"a":0,"k":0,"ix":6},"o":{"a":0,"k":100,"ix":7},"sk":{"a":0,"k":0,"ix":4},"sa":{"a":0,"k":0,"ix":5},"nm":"Transform"}],"nm":"Group 6","np":2,"cix":2,"bm":0,"ix":6,"mn":"ADBE Vector Group","hd":false},{"ty":"gr","it":[{"ind":0,"ty":"sh","ix":1,"ks":{"a":0,"k":{"i":[[1.879,-0.175],[0.175,1.878],[-22.988,2.137],[-0.174,-1.879],[1.879,-0.174],[-1.788,-19.238]],"o":[[-1.879,0.175],[-2.137,-22.989],[1.879,-0.175],[0.175,1.878],[-19.238,1.789],[0.175,1.879]],"v":[[-16.068,24.327],[-19.786,21.241],[18.029,-24.326],[21.747,-21.24],[18.662,-17.523],[-12.983,20.608]],"c":true},"ix":2},"nm":"Path 1","mn":"ADBE Vector Shape - Group","hd":false},{"ty":"fl","c":{"a":0,"k":[0.203921583587,0.219607858097,0.20000001496,1],"ix":4},"o":{"a":0,"k":100,"ix":5},"r":1,"bm":0,"nm":"Fill 1","mn":"ADBE Vector Graphic - Fill","hd":false},{"ty":"tr","p":{"a":0,"k":[262.597,251.303],"ix":2},"a":{"a":0,"k":[0,0],"ix":1},"s":{"a":0,"k":[100,100],"ix":3},"r":{"a":0,"k":0,"ix":6},"o":{"a":0,"k":100,"ix":7},"sk":{"a":0,"k":0,"ix":4},"sa":{"a":0,"k":0,"ix":5},"nm":"Transform"}],"nm":"Group 7","np":2,"cix":2,"bm":0,"ix":7,"mn":"ADBE Vector Group","hd":false},{"ty":"gr","it":[{"ind":0,"ty":"sh","ix":1,"ks":{"a":0,"k":{"i":[[1.585,-0.105],[0.234,0.032],[-0.257,1.869],[0.212,3.258],[26.466,-1.723],[8.429,-10.515],[1.473,1.181],[-1.181,1.473],[-15.349,1],[-1.968,-30.225],[0.504,-3.659]],"o":[[-0.226,0.015],[-1.869,-0.257],[0.441,-3.205],[-1.724,-26.465],[-13.44,0.876],[-1.179,1.473],[-1.472,-1.18],[9.625,-12.009],[30.225,-1.968],[0.242,3.716],[-0.225,1.636]],"v":[[45.758,33.629],[45.066,33.603],[42.148,29.753],[42.492,20.013],[-8.63,-24.857],[-43.042,-6.933],[-47.844,-6.404],[-48.372,-11.206],[-9.074,-31.675],[49.311,19.569],[48.917,30.684]],"c":true},"ix":2},"nm":"Path 1","mn":"ADBE Vector Shape - Group","hd":false},{"ty":"fl","c":{"a":0,"k":[0.203921583587,0.219607858097,0.20000001496,1],"ix":4},"o":{"a":0,"k":100,"ix":5},"r":1,"bm":0,"nm":"Fill 1","mn":"ADBE Vector Graphic - Fill","hd":false},{"ty":"tr","p":{"a":0,"k":[172.312,232.518],"ix":2},"a":{"a":0,"k":[0,0],"ix":1},"s":{"a":0,"k":[100,100],"ix":3},"r":{"a":0,"k":0,"ix":6},"o":{"a":0,"k":100,"ix":7},"sk":{"a":0,"k":0,"ix":4},"sa":{"a":0,"k":0,"ix":5},"nm":"Transform"}],"nm":"Group 8","np":2,"cix":2,"bm":0,"ix":8,"mn":"ADBE Vector Group","hd":false},{"ty":"gr","it":[{"ind":0,"ty":"sh","ix":1,"ks":{"a":0,"k":{"i":[[0.556,-4.822],[0,0],[0,0],[0,0],[0,0],[-2.574,-3.189]],"o":[[0,0],[0,0],[0,0],[0,0],[4.246,0.4],[2.787,3.45]],"v":[[70.926,13.261],[66.049,43.158],[0.28,43.158],[0.28,-11.364],[56.993,-5.234],[67.419,0.251]],"c":true},"ix":2},"nm":"Path 1","mn":"ADBE Vector Shape - Group","hd":false},{"ind":1,"ty":"sh","ix":2,"ks":{"a":0,"k":{"i":[[0,0],[0,0],[0,0],[0,0],[0,0],[0,0]],"o":[[0,0],[0,0],[0,0],[0,0],[0,0],[0,0]],"v":[[-65.244,-43.053],[-6.553,-43.053],[-6.553,-39.064],[-6.553,-12.102],[-6.553,43.158],[-65.244,43.158]],"c":true},"ix":2},"nm":"Path 2","mn":"ADBE Vector Shape - Group","hd":false},{"ind":2,"ty":"sh","ix":3,"ks":{"a":0,"k":{"i":[[3.949,4.891],[5.984,0.564],[0,0],[0,0],[0,0],[0,0],[0,1.887],[1.886,0],[0,0],[0,0],[0,0],[0,0],[0,-1.886],[-1.886,0],[0,0],[0,0],[0,0],[0,0],[0,0]],"o":[[-3.705,-4.588],[0,0],[0,0],[0,0],[0,0],[1.886,0],[0,-1.886],[0,0],[0,0],[0,0],[0,0],[-1.886,0],[0,1.887],[0,0],[0,0],[0,0],[0,0],[0,0],[0.792,-6.663]],"v":[[72.737,-4.041],[57.685,-12.032],[0.28,-18.124],[0.28,-39.064],[0.28,-43.053],[2.814,-43.053],[6.23,-46.47],[2.814,-49.886],[0.28,-49.886],[-72.077,-49.991],[-72.077,-49.886],[-75.078,-49.886],[-78.494,-46.47],[-75.078,-43.053],[-72.077,-43.053],[-72.077,49.991],[71.857,49.991],[77.682,14.285],[77.703,14.139]],"c":true},"ix":2},"nm":"Path 3","mn":"ADBE Vector Shape - Group","hd":false},{"ty":"mm","mm":1,"nm":"Merge Paths 1","mn":"ADBE Vector Filter - Merge","hd":false},{"ty":"fl","c":{"a":0,"k":[0.203921583587,0.219607858097,0.20000001496,1],"ix":4},"o":{"a":0,"k":100,"ix":5},"r":1,"bm":0,"nm":"Fill 1","mn":"ADBE Vector Graphic - Fill","hd":false},{"ty":"tr","p":{"a":0,"k":[235.943,217.248],"ix":2},"a":{"a":0,"k":[0,0],"ix":1},"s":{"a":0,"k":[100,100],"ix":3},"r":{"a":0,"k":0,"ix":6},"o":{"a":0,"k":100,"ix":7},"sk":{"a":0,"k":0,"ix":4},"sa":{"a":0,"k":0,"ix":5},"nm":"Transform"}],"nm":"Group 9","np":5,"cix":2,"bm":0,"ix":9,"mn":"ADBE Vector Group","hd":false},{"ty":"gr","it":[{"ind":0,"ty":"sh","ix":1,"ks":{"a":0,"k":{"i":[[0,0],[0,0],[0,0],[14.218,10.071],[0,0],[0,0],[0,0],[0,0],[0,0],[0,0],[11.971,1.141]],"o":[[0,0],[0,0],[0,0],[-16.639,-11.785],[0,0],[0,0],[0,0],[0,0],[0,0],[1.403,-11.943],[0,0]],"v":[[-7.657,-32.906],[-7.531,-2.636],[-24.386,-2.636],[-42.416,-19.205],[-73.909,-30.154],[-73.909,32.906],[-33.878,32.906],[-5.418,32.906],[66.867,32.906],[72.506,-2.099],[54.613,-25.945]],"c":true},"ix":2},"nm":"Path 1","mn":"ADBE Vector Shape - Group","hd":false},{"ty":"fl","c":{"a":0,"k":[0,0.556862745098,0.956862804936,1],"ix":4},"o":{"a":0,"k":100,"ix":5},"r":1,"bm":0,"nm":"Fill 1","mn":"ADBE Vector Graphic - Fill","hd":false},{"ty":"tr","p":{"a":0,"k":[240.629,233.89],"ix":2},"a":{"a":0,"k":[0,0],"ix":1},"s":{"a":0,"k":[100,100],"ix":3},"r":{"a":0,"k":0,"ix":6},"o":{"a":0,"k":100,"ix":7},"sk":{"a":0,"k":0,"ix":4},"sa":{"a":0,"k":0,"ix":5},"nm":"Transform"}],"nm":"Group 10","np":2,"cix":2,"bm":0,"ix":10,"mn":"ADBE Vector Group","hd":false},{"ty":"gr","it":[{"ind":0,"ty":"sh","ix":1,"ks":{"a":0,"k":{"i":[[0,0],[0,0],[0,0],[0,0],[0,0],[0,0],[0,0],[0,0],[11.971,1.141]],"o":[[0,0],[0,0],[0,0],[0,0],[0,0],[0,0],[0,0],[1.403,-11.943],[0,0]],"v":[[-5.418,-18.313],[-5.418,-47.499],[-73.909,-47.499],[-73.909,47.499],[-33.879,47.499],[-5.418,47.499],[66.866,47.499],[72.506,12.493],[54.613,-11.352]],"c":true},"ix":2},"nm":"Path 1","mn":"ADBE Vector Shape - Group","hd":false},{"ty":"fl","c":{"a":0,"k":[0.87450986376,0.909803981407,0.937254961799,1],"ix":4},"o":{"a":0,"k":100,"ix":5},"r":1,"bm":0,"nm":"Fill 1","mn":"ADBE Vector Graphic - Fill","hd":false},{"ty":"tr","p":{"a":0,"k":[240.629,219.297],"ix":2},"a":{"a":0,"k":[0,0],"ix":1},"s":{"a":0,"k":[100,100],"ix":3},"r":{"a":0,"k":0,"ix":6},"o":{"a":0,"k":100,"ix":7},"sk":{"a":0,"k":0,"ix":4},"sa":{"a":0,"k":0,"ix":5},"nm":"Transform"}],"nm":"Group 11","np":2,"cix":2,"bm":0,"ix":11,"mn":"ADBE Vector Group","hd":false}],"ip":0,"op":115,"st":0,"bm":0},{"ddd":0,"ind":8,"ty":4,"nm":"Chmney Outlines","parent":7,"sr":1,"ks":{"o":{"a":0,"k":100,"ix":11},"r":{"a":1,"k":[{"i":{"x":[0.667],"y":[1]},"o":{"x":[0.333],"y":[0]},"t":7,"s":[0]},{"i":{"x":[0.667],"y":[1]},"o":{"x":[0.333],"y":[0]},"t":11,"s":[10.058]},{"i":{"x":[0.667],"y":[1]},"o":{"x":[0.333],"y":[0]},"t":14,"s":[0]},{"i":{"x":[0.667],"y":[1]},"o":{"x":[0.333],"y":[0]},"t":34,"s":[0]},{"i":{"x":[0.667],"y":[1]},"o":{"x":[0.333],"y":[0]},"t":38,"s":[10.058]},{"i":{"x":[0.667],"y":[1]},"o":{"x":[0.333],"y":[0]},"t":41,"s":[0]},{"i":{"x":[0.667],"y":[1]},"o":{"x":[0.333],"y":[0]},"t":61,"s":[0]},{"i":{"x":[0.667],"y":[1]},"o":{"x":[0.333],"y":[0]},"t":65,"s":[10.058]},{"i":{"x":[0.667],"y":[1]},"o":{"x":[0.333],"y":[0]},"t":68,"s":[0]},{"i":{"x":[0.667],"y":[1]},"o":{"x":[0.333],"y":[0]},"t":88,"s":[0]},{"i":{"x":[0.667],"y":[1]},"o":{"x":[0.333],"y":[0]},"t":92,"s":[10.058]},{"t":95,"s":[0]}],"ix":10},"p":{"a":0,"k":[268.5,207,0],"ix":2,"l":2},"a":{"a":0,"k":[268.5,207,0],"ix":1,"l":2},"s":{"a":0,"k":[100,100,100],"ix":6,"l":2}},"ao":0,"shapes":[{"ty":"gr","it":[{"ind":0,"ty":"sh","ix":1,"ks":{"a":0,"k":{"i":[[0,0],[0,0],[0,0],[0,0]],"o":[[0,0],[0,0],[0,0],[0,0]],"v":[[-3.961,3.873],[3.961,4.68],[3.961,-5.585],[-3.961,-5.585]],"c":true},"ix":2},"nm":"Path 1","mn":"ADBE Vector Shape - Group","hd":false},{"ind":1,"ty":"sh","ix":2,"ks":{"a":0,"k":{"i":[[1.087,0],[0.15,0.016],[0,0],[0,4.578],[0,0],[-2.434,0],[0,0],[0,-2.434],[0,0]],"o":[[-0.149,0],[0,0],[-2.263,-0.233],[0,0],[0,-2.434],[0,0],[2.435,0],[0,0],[0,5.206]],"v":[[5.012,10.259],[4.564,10.236],[-5.46,9.214],[-9.427,4.823],[-9.427,-6.636],[-5.013,-11.051],[5.013,-11.051],[9.427,-6.636],[9.427,5.845]],"c":true},"ix":2},"nm":"Path 2","mn":"ADBE Vector Shape - Group","hd":false},{"ty":"mm","mm":1,"nm":"Merge Paths 1","mn":"ADBE Vector Filter - Merge","hd":false},{"ty":"fl","c":{"a":0,"k":[0.203921583587,0.219607858097,0.20000001496,1],"ix":4},"o":{"a":0,"k":100,"ix":5},"r":1,"bm":0,"nm":"Fill 1","mn":"ADBE Vector Graphic - Fill","hd":false},{"ty":"tr","p":{"a":0,"k":[267.776,198.177],"ix":2},"a":{"a":0,"k":[0,0],"ix":1},"s":{"a":0,"k":[100,100],"ix":3},"r":{"a":0,"k":0,"ix":6},"o":{"a":0,"k":100,"ix":7},"sk":{"a":0,"k":0,"ix":4},"sa":{"a":0,"k":0,"ix":5},"nm":"Transform"}],"nm":"Group 1","np":4,"cix":2,"bm":0,"ix":1,"mn":"ADBE Vector Group","hd":false},{"ty":"gr","it":[{"ind":0,"ty":"sh","ix":1,"ks":{"a":0,"k":{"i":[[0.727,0.074],[0,0],[0,0.633],[0,0],[-0.715,0],[0,0],[0,-0.681],[0,0]],"o":[[0,0],[-0.63,-0.064],[0,0],[0,-0.715],[0,0],[0.682,0],[0,0],[0,0.731]],"v":[[5.335,7.906],[-5.585,6.791],[-6.694,5.564],[-6.694,-6.685],[-5.4,-7.98],[5.46,-7.98],[6.694,-6.746],[6.694,6.678]],"c":true},"ix":2},"nm":"Path 1","mn":"ADBE Vector Shape - Group","hd":false},{"ty":"fl","c":{"a":0,"k":[0,0.556862745098,0.956862804936,1],"ix":4},"o":{"a":0,"k":100,"ix":5},"r":1,"bm":0,"nm":"Fill 1","mn":"ADBE Vector Graphic - Fill","hd":false},{"ty":"tr","p":{"a":0,"k":[267.775,197.839],"ix":2},"a":{"a":0,"k":[0,0],"ix":1},"s":{"a":0,"k":[100,100],"ix":3},"r":{"a":0,"k":0,"ix":6},"o":{"a":0,"k":100,"ix":7},"sk":{"a":0,"k":0,"ix":4},"sa":{"a":0,"k":0,"ix":5},"nm":"Transform"}],"nm":"Group 2","np":2,"cix":2,"bm":0,"ix":2,"mn":"ADBE Vector Group","hd":false},{"ty":"gr","it":[{"ind":0,"ty":"sh","ix":1,"ks":{"a":0,"k":{"i":[[0,0],[0,0],[0,0],[0,0],[0,0],[0,0]],"o":[[0,0],[0,0],[0,0],[0,0],[0,0],[0,0]],"v":[[-2.792,8.238],[-0.591,8.238],[-0.591,-2.885],[2.547,-6.65],[1.532,-7.512],[-2.792,-2.848]],"c":true},"ix":2},"nm":"Path 1","mn":"ADBE Vector Shape - Group","hd":false},{"ind":1,"ty":"sh","ix":2,"ks":{"a":0,"k":{"i":[[0,0],[0,0],[0,0],[0,0],[-2.051,-1.743],[0,0],[-0.063,-1.383],[0.91,-0.981],[0,0]],"o":[[0,0],[0,0],[0,0],[1.829,-1.975],[0,0],[1.055,0.897],[0.062,1.34],[0,0],[0,0]],"v":[[4.875,13.704],[-8.258,13.704],[-8.258,-4.992],[-2.179,-11.549],[4.74,-11.96],[6.437,-10.519],[8.196,-6.93],[6.863,-3.291],[4.875,-0.907]],"c":true},"ix":2},"nm":"Path 2","mn":"ADBE Vector Shape - Group","hd":false},{"ty":"mm","mm":1,"nm":"Merge Paths 1","mn":"ADBE Vector Filter - Merge","hd":false},{"ty":"fl","c":{"a":0,"k":[0.203921583587,0.219607858097,0.20000001496,1],"ix":4},"o":{"a":0,"k":100,"ix":5},"r":1,"bm":0,"nm":"Fill 1","mn":"ADBE Vector Graphic - Fill","hd":false},{"ty":"tr","p":{"a":0,"k":[269.467,180.256],"ix":2},"a":{"a":0,"k":[0,0],"ix":1},"s":{"a":0,"k":[100,100],"ix":3},"r":{"a":0,"k":0,"ix":6},"o":{"a":0,"k":100,"ix":7},"sk":{"a":0,"k":0,"ix":4},"sa":{"a":0,"k":0,"ix":5},"nm":"Transform"}],"nm":"Group 3","np":4,"cix":2,"bm":0,"ix":3,"mn":"ADBE Vector Group","hd":false},{"ty":"gr","it":[{"ind":0,"ty":"sh","ix":1,"ks":{"a":0,"k":{"i":[[0,0],[0,0],[0,0],[0,0],[-0.929,-0.79],[0,0],[0.923,-0.944],[0,0]],"o":[[0,0],[0,0],[0,0],[0.829,-0.894],[0,0],[1.006,0.855],[0,0],[0,0]],"v":[[2.033,10.82],[-5.634,10.82],[-5.634,-4.071],[-0.285,-9.842],[2.86,-10.029],[4.557,-8.587],[4.71,-5.26],[2.033,-2.046]],"c":true},"ix":2},"nm":"Path 1","mn":"ADBE Vector Shape - Group","hd":false},{"ty":"fl","c":{"a":0,"k":[0.886274569642,0.925490255917,0.960784373564,1],"ix":4},"o":{"a":0,"k":100,"ix":5},"r":1,"bm":0,"nm":"Fill 1","mn":"ADBE Vector Graphic - Fill","hd":false},{"ty":"tr","p":{"a":0,"k":[269.576,180.407],"ix":2},"a":{"a":0,"k":[0,0],"ix":1},"s":{"a":0,"k":[100,100],"ix":3},"r":{"a":0,"k":0,"ix":6},"o":{"a":0,"k":100,"ix":7},"sk":{"a":0,"k":0,"ix":4},"sa":{"a":0,"k":0,"ix":5},"nm":"Transform"}],"nm":"Group 4","np":2,"cix":2,"bm":0,"ix":4,"mn":"ADBE Vector Group","hd":false}],"ip":0,"op":117,"st":-17,"bm":0},{"ddd":0,"ind":9,"ty":4,"nm":"white BG Outlines","sr":1,"ks":{"o":{"a":0,"k":100,"ix":11},"r":{"a":0,"k":0,"ix":10},"p":{"a":0,"k":[225,225,0],"ix":2,"l":2},"a":{"a":0,"k":[225,225,0],"ix":1,"l":2},"s":{"a":0,"k":[100,100,100],"ix":6,"l":2}},"ao":0,"shapes":[{"ty":"gr","it":[{"ind":0,"ty":"sh","ix":1,"ks":{"a":0,"k":{"i":[[6.576,0],[0,0],[0,10.538],[-8.573,0],[0,0],[0,-10.57],[0,0]],"o":[[0,0],[-10.539,0],[0,-8.574],[0,0],[10.571,0],[0,0],[0,6.575]],"v":[[26.37,17.302],[-19.195,17.302],[-38.277,-1.779],[-22.754,-17.303],[19.137,-17.303],[38.276,1.837],[38.276,5.396]],"c":true},"ix":2},"nm":"Path 1","mn":"ADBE Vector Shape - Group","hd":false},{"ty":"fl","c":{"a":0,"k":[1,1,1,1],"ix":4},"o":{"a":0,"k":100,"ix":5},"r":1,"bm":0,"nm":"Fill 1","mn":"ADBE Vector Graphic - Fill","hd":false},{"ty":"tr","p":{"a":0,"k":[222.173,237.919],"ix":2},"a":{"a":0,"k":[0,0],"ix":1},"s":{"a":0,"k":[100,100],"ix":3},"r":{"a":0,"k":0,"ix":6},"o":{"a":0,"k":100,"ix":7},"sk":{"a":0,"k":0,"ix":4},"sa":{"a":0,"k":0,"ix":5},"nm":"Transform"}],"nm":"Group 1","np":2,"cix":2,"bm":0,"ix":1,"mn":"ADBE Vector Group","hd":false}],"ip":0,"op":115,"st":0,"bm":0},{"ddd":0,"ind":10,"ty":4,"nm":"white stroke Outlines","sr":1,"ks":{"o":{"a":0,"k":100,"ix":11},"r":{"a":0,"k":0,"ix":10},"p":{"a":0,"k":[225,225,0],"ix":2,"l":2},"a":{"a":0,"k":[225,225,0],"ix":1,"l":2},"s":{"a":0,"k":[100,100,100],"ix":6,"l":2}},"ao":0,"shapes":[{"ty":"gr","it":[{"ind":0,"ty":"sh","ix":1,"ks":{"a":0,"k":{"i":[[0,-1.712],[36.766,0],[0,1.712],[-36.766,0]],"o":[[0,1.712],[-36.766,0],[0,-1.712],[36.766,0]],"v":[[66.571,0],[0,3.101],[-66.571,0],[0,-3.101]],"c":true},"ix":2},"nm":"Path 1","mn":"ADBE Vector Shape - Group","hd":false},{"ty":"fl","c":{"a":0,"k":[0.666666666667,0.647058823529,0.607843137255,1],"ix":4},"o":{"a":0,"k":100,"ix":5},"r":1,"bm":0,"nm":"Fill 1","mn":"ADBE Vector Graphic - Fill","hd":false},{"ty":"tr","p":{"a":0,"k":[226.367,298.779],"ix":2},"a":{"a":0,"k":[0,0],"ix":1},"s":{"a":0,"k":[100,100],"ix":3},"r":{"a":0,"k":0,"ix":6},"o":{"a":0,"k":100,"ix":7},"sk":{"a":0,"k":0,"ix":4},"sa":{"a":0,"k":0,"ix":5},"nm":"Transform"}],"nm":"Group 1","np":2,"cix":2,"bm":0,"ix":1,"mn":"ADBE Vector Group","hd":false},{"ty":"gr","it":[{"ind":0,"ty":"sh","ix":1,"ks":{"a":0,"k":{"i":[[0,0],[0,0],[0,0],[0,0],[0,0],[0,0],[3.949,4.891],[5.984,0.563],[0,0],[0,0],[1.667,0.632],[0,0],[0,0],[0.062,1.34],[1.055,0.896],[0,0],[1.829,-1.975],[0,0],[0,0],[0,-1.885],[0,0],[0,0],[0,0],[0,0],[0,0],[0,1.887],[1.887,0],[0,0],[0,0],[0,0],[0,0],[0,-1.886],[-1.887,0],[0,0],[0,0],[0.21,-0.014],[9.625,-12.009],[-1.472,-1.18],[-1.179,1.473],[-13.44,0.876],[-0.062,0.004],[0,0],[0,0],[0,0],[0,0],[0,0],[0,0],[0,0],[0,0],[0,0],[0,0],[0,0],[0,0],[0,0],[0,0],[0,0],[0,0],[0,0],[0,0],[0,0],[0,0],[0,0],[0,0],[0,0],[0,0],[0,0],[0,0],[0,0],[0,0],[0,0],[-0.166,-1.789],[-1.879,0.175],[0.174,1.879],[-0.063,1.541],[0,0],[0,0],[0,0],[0,0],[0,0],[0,0],[0,0],[0,0],[0,0],[0,0],[0,0],[0,0],[0,0],[0,0],[0,0],[0,0],[0,0],[0,0],[0,0],[0,0]],"o":[[0,0],[0,0],[0,0],[0,0],[0,0],[0.793,-6.663],[-3.704,-4.588],[0,0],[0,0],[0,-1.886],[0,0],[0,0],[0.91,-0.981],[-0.063,-1.383],[0,0],[-2.051,-1.743],[0,0],[0,0],[-1.667,0.632],[0,0],[0,0],[0,0],[0,0],[0,0],[1.887,0],[0,-1.886],[0,0],[0,0],[0,0],[0,0],[-1.887,0],[0,1.887],[0,0],[0,0],[-0.21,0.011],[-15.349,1],[-1.181,1.472],[1.473,1.181],[8.429,-10.515],[0.062,-0.004],[0,0],[0,0],[0,0],[0,0],[0,0],[0,0],[0,0],[0,0],[0,0],[0,0],[0,0],[0,0],[0,0],[0,0],[0,0],[0,0],[0,0],[0,0],[0,0],[0,0],[0,0],[0,0],[0,0],[0,0],[0,0],[0,0],[0,0],[0,0],[0,0],[-0.059,1.751],[0.175,1.879],[1.879,-0.175],[-0.147,-1.577],[0,0],[0,0],[0,0],[0,0],[0,0],[0,0],[0,0],[0,0],[0,0],[0,0],[0,0],[0,0],[0,0],[0,0],[0,0],[0,0],[0,0],[0,0],[0,0],[0,0],[0,0]],"v":[[95.727,34.977],[94.025,30.066],[94.009,24.87],[91.341,21.462],[95.026,-1.133],[95.047,-1.279],[90.081,-19.458],[75.03,-27.449],[58.604,-29.193],[58.604,-41.125],[55.743,-45.242],[55.743,-53.316],[57.732,-55.702],[59.065,-59.341],[57.306,-62.927],[55.608,-64.37],[48.69,-63.958],[42.611,-57.401],[42.611,-45.242],[39.75,-41.125],[39.75,-31.193],[17.624,-33.542],[17.624,-54.482],[17.624,-58.47],[20.158,-58.47],[23.574,-61.888],[20.158,-65.303],[17.624,-65.303],[-54.732,-65.409],[-54.732,-65.303],[-57.734,-65.303],[-61.15,-61.888],[-57.734,-58.47],[-54.732,-58.47],[-54.732,-31.848],[-55.361,-31.823],[-94.658,-11.354],[-94.13,-6.551],[-89.328,-7.081],[-54.917,-25.005],[-54.732,-25.007],[-54.732,-22.809],[-61.436,-19.845],[-68.857,-19.208],[-74.324,-14.147],[-81.135,-11.134],[-84.661,-4.574],[-90.126,0.488],[-91.331,7.839],[-94.857,14.4],[-93.609,21.743],[-94.813,29.094],[-91.249,35.635],[-90.001,42.979],[-84.505,48.008],[-80.941,54.547],[-74.111,57.52],[-68.615,62.549],[-61.191,63.142],[-54.361,66.113],[-47.145,64.263],[-39.719,64.857],[-33.497,60.763],[-26.281,58.914],[-21.723,53.023],[-15.499,48.93],[-13.102,41.878],[-8.543,35.986],[-8.548,34.573],[24.094,34.573],[24.212,39.878],[27.931,42.965],[31.017,39.247],[30.931,34.573],[34.62,34.573],[34.719,35.158],[33.88,40.286],[36.367,44.849],[37.238,49.973],[41.072,53.48],[43.559,58.044],[48.323,60.117],[52.158,63.626],[57.337,64.039],[62.104,66.113],[67.138,64.823],[72.318,65.237],[76.66,62.382],[81.694,61.091],[84.875,56.979],[89.216,54.125],[90.889,49.204],[94.069,45.094],[94.053,39.896]],"c":true},"ix":2},"nm":"Path 1","mn":"ADBE Vector Shape - Group","hd":false},{"ty":"st","c":{"a":0,"k":[1,1,1,1],"ix":3},"o":{"a":0,"k":100,"ix":4},"w":{"a":0,"k":3,"ix":5},"lc":1,"lj":1,"ml":10,"bm":0,"nm":"Stroke 1","mn":"ADBE Vector Graphic - Stroke","hd":false},{"ty":"tr","p":{"a":0,"k":[218.599,232.665],"ix":2},"a":{"a":0,"k":[0,0],"ix":1},"s":{"a":0,"k":[100,100],"ix":3},"r":{"a":0,"k":0,"ix":6},"o":{"a":0,"k":100,"ix":7},"sk":{"a":0,"k":0,"ix":4},"sa":{"a":0,"k":0,"ix":5},"nm":"Transform"}],"nm":"Group 2","np":2,"cix":2,"bm":0,"ix":2,"mn":"ADBE Vector Group","hd":false}],"ip":0,"op":115,"st":0,"bm":0},{"ddd":0,"ind":11,"ty":0,"nm":"fence","refId":"comp_0","sr":1,"ks":{"o":{"a":0,"k":100,"ix":11},"r":{"a":0,"k":0,"ix":10},"p":{"a":0,"k":[225,225,0],"ix":2,"l":2},"a":{"a":0,"k":[225,225,0],"ix":1,"l":2},"s":{"a":0,"k":[100,100,100],"ix":6,"l":2}},"ao":0,"hasMask":true,"masksProperties":[{"inv":false,"mode":"a","pt":{"a":0,"k":{"i":[[0,0],[0,0],[0,0],[0,0]],"o":[[0,0],[0,0],[0,0],[0,0]],"v":[[387.25,130],[59,130],[59,328],[387.25,328]],"c":true},"ix":1},"o":{"a":0,"k":100,"ix":3},"x":{"a":0,"k":0,"ix":4},"nm":"Mask 1"}],"w":450,"h":450,"ip":0,"op":115,"st":0,"bm":0}],"markers":[]}